Workbook
Name Status: Projects!$P$6

Sheet Projects
R1: Contracted
R2: Checking
R3: Not contracted
R4: #N/A
A5: Project | B5: S/N | C5: PO Number | D5: Delivery Stage | E5: PO Name | F5: PO Name [Standardized] | G5: Account Code | H5: Category | I5: Status | J5: PO Issue Date | K5: Req. Delivery Date | L5: Vessel Category | M5: Po Value | N5: Po Currency | O5: Supplier Name | P5: Contract Status
A6: Glovis Luminous | C6: GLUM-60015/26-1 | D6: =IF(OR(ISNUMBER(SEARCH("Pre Delivery",E6)),ISNUMBER(SEARCH("Pre-Delivery",E6)),ISNUMBER(SEARCH("Predelivery",E6)),ISNUMBER(SEARCH("PD -",E6)),ISNUMBER(SEARCH("PD Lubes",E6))),"Pre-Delivery","") -> Pre-Delivery | E6: PD - RSC Envirologic | F6: Lubricants | H6: Spares | I6: PO Created | L6: PCTC | M6: #N/A | N6: #N/A | O6: #N/A | P6: #N/A
A7: Glovis Luminous | C7: GLUM-60003/26-1 | D7: =IF(OR(ISNUMBER(SEARCH("Pre Delivery",E7)),ISNUMBER(SEARCH("Pre-Delivery",E7)),ISNUMBER(SEARCH("Predelivery",E7)),ISNUMBER(SEARCH("PD -",E7)),ISNUMBER(SEARCH("PD Lubes",E7))),"Pre-Delivery","") | E7: FS-ITBP -luminous | F7: IT Equipment - ITBP | H7: Spares | I7: Pending Delivery | J7: 46055 | L7: PCTC | M7: #N/A | N7: #N/A | O7: #N/A | P7: #N/A
A8: Glovis Luminous | C8: GLUM-MVSP-60002/26-1 | D8: =IF(OR(ISNUMBER(SEARCH("Pre Delivery",E8)),ISNUMBER(SEARCH("Pre-Delivery",E8)),ISNUMBER(SEARCH("Predelivery",E8)),ISNUMBER(SEARCH("PD -",E8)),ISNUMBER(SEARCH("PD Lubes",E8))),"Pre-Delivery","") | E8: FS-X10-SILVERPEAK | F8: IT Equipment - X10 System | H8: Spares | I8: Pending Supplier Confirmation | J8: 46101 | L8: PCTC | M8: #N/A | N8: #N/A | O8: #N/A | P8: #N/A
A9: Glovis Luminous | C9: GLUM-60024/26-1 | D9: =IF(OR(ISNUMBER(SEARCH("Pre Delivery",E9)),ISNUMBER(SEARCH("Pre-Delivery",E9)),ISNUMBER(SEARCH("Predelivery",E9)),ISNUMBER(SEARCH("PD -",E9)),ISNUMBER(SEARCH("PD Lubes",E9))),"Pre-Delivery","") | E9: Service: LNG OPERATION MANUAL Development | F9: LNG Operation Manual | H9: Spares | I9: PO Created | L9: PCTC | M9: #N/A | N9: #N/A | O9: #N/A | P9: #N/A
A10: Glovis Luminous | C10: GLUM-60006/26-1 | D10: =IF(OR(ISNUMBER(SEARCH("Pre Delivery",E10)),ISNUMBER(SEARCH("Pre-Delivery",E10)),ISNUMBER(SEARCH("Predelivery",E10)),ISNUMBER(SEARCH("PD -",E10)),ISNUMBER(SEARCH("PD Lubes",E10))),"Pre-Delivery","") | E10: Shipyard Extra Buyers Supply - Tripods and Spray Pipes | F10: Tripods & Spray Pipes | H10: Spares | I10: Pending Delivery | J10: 46091 | L10: PCTC | M10: #N/A | N10: #N/A | O10: #N/A | P10: #N/A
A11: Glovis Luminous | C11: GLUM-60019/26-1 | D11: =IF(OR(ISNUMBER(SEARCH("Pre Delivery",E11)),ISNUMBER(SEARCH("Pre-Delivery",E11)),ISNUMBER(SEARCH("Predelivery",E11)),ISNUMBER(SEARCH("PD -",E11)),ISNUMBER(SEARCH("PD Lubes",E11))),"Pre-Delivery","") | E11: Shipyard Extra (buyer Supply) - QCDC -GSI | F11: QCDC | H11: Spares | I11: Pending Supplier Confirmation | J11: 46101 | L11: PCTC | M11: #N/A | N11: #N/A | O11: #N/A | P11: #N/A
A12: Glovis Luminous | C12: GLUM-60016/26-1 | D12: =IF(OR(ISNUMBER(SEARCH("Pre Delivery",E12)),ISNUMBER(SEARCH("Pre-Delivery",E12)),ISNUMBER(SEARCH("Predelivery",E12)),ISNUMBER(SEARCH("PD -",E12)),ISNUMBER(SEARCH("PD Lubes",E12))),"Pre-Delivery","") | E12: Reliabiltiy Spares - Gas Detection System | F12: Gas Detection System | H12: Spares | I12: Pending Delivery | J12: 46087 | L12: PCTC | M12: #N/A | N12: #N/A | O12: #N/A | P12: #N/A
A13: Glovis Luminous | C13: GLUM-60008/26-1 | D13: =IF(OR(ISNUMBER(SEARCH("Pre Delivery",E13)),ISNUMBER(SEARCH("Pre-Delivery",E13)),ISNUMBER(SEARCH("Predelivery",E13)),ISNUMBER(SEARCH("PD -",E13)),ISNUMBER(SEARCH("PD Lubes",E13))),"Pre-Delivery","") | E13: Shipyard Extra Buyers Supply - Hinas SVM SEASPAN 10.8K PCTC | F13: Navigation - HiNAS SVM | H13: Spares | I13: Pending Supplier Confirmation | J13: 46070 | L13: PCTC | M13: #N/A | N13: #N/A | O13: #N/A | P13: #N/A
A14: Glovis Luminous | C14: GLUM-60010/26-1 | D14: =IF(OR(ISNUMBER(SEARCH("Pre Delivery",E14)),ISNUMBER(SEARCH("Pre-Delivery",E14)),ISNUMBER(SEARCH("Predelivery",E14)),ISNUMBER(SEARCH("PD -",E14)),ISNUMBER(SEARCH("PD Lubes",E14))),"Pre-Delivery","") | E14: FS-ITBP Additional Item | F14: IT Equipment - ITBP Additional Items | H14: Spares | I14: Pending Delivery | J14: 46072 | L14: PCTC | M14: #N/A | N14: #N/A | O14: #N/A | P14: #N/A
A15: Glovis Luminous | C15: GLUM-60023/26-1 | D15: =IF(OR(ISNUMBER(SEARCH("Pre Delivery",E15)),ISNUMBER(SEARCH("Pre-Delivery",E15)),ISNUMBER(SEARCH("Predelivery",E15)),ISNUMBER(SEARCH("PD -",E15)),ISNUMBER(SEARCH("PD Lubes",E15))),"Pre-Delivery","") -> Pre-Delivery | E15: Pre Delivery - FLIR Camera | F15: Thermal Camera (FLIR) | H15: Spares | I15: Pending Delivery | J15: 46099 | L15: PCTC | M15: #N/A | N15: #N/A | O15: #N/A | P15: #N/A
A16: Glovis Luminous | C16: GLUM-60001/26-1 | D16: =IF(OR(ISNUMBER(SEARCH("Pre Delivery",E16)),ISNUMBER(SEARCH("Pre-Delivery",E16)),ISNUMBER(SEARCH("Predelivery",E16)),ISNUMBER(SEARCH("PD -",E16)),ISNUMBER(SEARCH("PD Lubes",E16))),"Pre-Delivery","") | E16: Shipyard Extra Owner supply - Captains Eye | F16: Navigation - Captains Eye | H16: Spares | I16: Pending Delivery | J16: 46037 | L16: PCTC | M16: #N/A | N16: #N/A | O16: #N/A | P16: #N/A
A17: Glovis Luminous | C17: GLUM-60017/26-1 | D17: =IF(OR(ISNUMBER(SEARCH("Pre Delivery",E17)),ISNUMBER(SEARCH("Pre-Delivery",E17)),ISNUMBER(SEARCH("Predelivery",E17)),ISNUMBER(SEARCH("PD -",E17)),ISNUMBER(SEARCH("PD Lubes",E17))),"Pre-Delivery","") | E17: Reliability Spares - Fire detection system | F17: Fire Detection System | H17: Spares | I17: Pending Delivery | J17: 46087 | L17: PCTC | M17: #N/A | N17: #N/A | O17: #N/A | P17: #N/A
A18: Glovis Luminous | C18: GLUM-60002/26-1 | D18: =IF(OR(ISNUMBER(SEARCH("Pre Delivery",E18)),ISNUMBER(SEARCH("Pre-Delivery",E18)),ISNUMBER(SEARCH("Predelivery",E18)),ISNUMBER(SEARCH("PD -",E18)),ISNUMBER(SEARCH("PD Lubes",E18))),"Pre-Delivery","") | E18: FS-KVH-GSI | F18: Communications - VSAT (KVH) | H18: Spares | I18: Pending Delivery | J18: 46048 | L18: PCTC | M18: #N/A | N18: #N/A | O18: #N/A | P18: #N/A
A19: Glovis Luminous | C19: GLUM-60022/26-1 | D19: =IF(OR(ISNUMBER(SEARCH("Pre Delivery",E19)),ISNUMBER(SEARCH("Pre-Delivery",E19)),ISNUMBER(SEARCH("Predelivery",E19)),ISNUMBER(SEARCH("PD -",E19)),ISNUMBER(SEARCH("PD Lubes",E19))),"Pre-Delivery","") -> Pre-Delivery | E19: Pre Delivery - Sample Cooler | F19: Sample Cooler | H19: Spares | I19: Pending Supplier Confirmation | J19: 46101 | L19: PCTC | M19: #N/A | N19: #N/A | O19: #N/A | P19: #N/A
A20: Glovis Luminous | C20: GLUM-60009/26-1 | D20: =IF(OR(ISNUMBER(SEARCH("Pre Delivery",E20)),ISNUMBER(SEARCH("Pre-Delivery",E20)),ISNUMBER(SEARCH("Predelivery",E20)),ISNUMBER(SEARCH("PD -",E20)),ISNUMBER(SEARCH("PD Lubes",E20))),"Pre-Delivery","") | E20: FS-ITBP CABLES | F20: IT Equipment - ITBP Cables | H20: Spares | I20: Pending Supplier Confirmation | J20: 46071 | L20: PCTC | M20: #N/A | N20: #N/A | O20: #N/A | P20: #N/A
A21: Glovis Luminous | C21: GLUM-60007/26-1 | D21: =IF(OR(ISNUMBER(SEARCH("Pre Delivery",E21)),ISNUMBER(SEARCH("Pre-Delivery",E21)),ISNUMBER(SEARCH("Predelivery",E21)),ISNUMBER(SEARCH("PD -",E21)),ISNUMBER(SEARCH("PD Lubes",E21))),"Pre-Delivery","") | E21: FS-LENOVO-Luminous | F21: IT Equipment - Computers (Lenovo) | H21: Spares | I21: Pending Delivery | J21: 46066 | L21: PCTC | M21: #N/A | N21: #N/A | O21: #N/A | P21: #N/A
... A27: Glovis Luminous | C27: GLUM-60005/26-1 | D27: =IF(OR(ISNUMBER(SEARCH("Pre Delivery",E27)),ISNUMBER(SEARCH("Pre-Delivery",E27)),ISNUMBER(SEARCH("Predelivery",E27)),ISNUMBER(SEARCH("PD -",E27)),ISNUMBER(SEARCH("PD Lubes",E27))),"Pre-Delivery","") | E27: SHIPYARD EXTRA ONWER SUPPLY - Abanaki Skimmers | F27: Oil Skimmers - Abanaki | H27: Spares | I27: Pending Supplier Confirmation | J27: 46065 | L27: PCTC | M27: #N/A | N27: #N/A | O27: #N/A | P27: #N/A
A28: Glovis Luminous | C28: GLUM-60014/26 | D28: =IF(OR(ISNUMBER(SEARCH("Pre Delivery",E28)),ISNUMBER(SEARCH("Pre-Delivery",E28)),ISNUMBER(SEARCH("Predelivery",E28)),ISNUMBER(SEARCH("PD -",E28)),ISNUMBER(SEARCH("PD Lubes",E28))),"Pre-Delivery","") | E28: Reliability Spares - PCTC-Seaspan - Boilers QUOT26012103 | F28: Boiler Spares | H28: Spares | I28: Pending Approval | J28: 46078 | K28: To be Approved | L28: PCTC | M28: #N/A | N28: #N/A | O28: #N/A | P28: #N/A
A29: Glovis Luminous | C29: GLUM-60025/26 | D29: =IF(OR(ISNUMBER(SEARCH("Pre Delivery",E29)),ISNUMBER(SEARCH("Pre-Delivery",E29)),ISNUMBER(SEARCH("Predelivery",E29)),ISNUMBER(SEARCH("PD -",E29)),ISNUMBER(SEARCH("PD Lubes",E29))),"Pre-Delivery","") | E29: Ultrasonic Cleaner | F29: Ultrasonic Cleaner | H29: Stores | I29: Pending Approval | K29: To be Approved | L29: PCTC | M29: #N/A | N29: #N/A | O29: #N/A | P29: #N/A
A30: Glovis Luminous | C30: GLUM-60026/26 | D30: =IF(OR(ISNUMBER(SEARCH("Pre Delivery",E30)),ISNUMBER(SEARCH("Pre-Delivery",E30)),ISNUMBER(SEARCH("Predelivery",E30)),ISNUMBER(SEARCH("PD -",E30)),ISNUMBER(SEARCH("PD Lubes",E30))),"Pre-Delivery","") | E30: OPA 90 KIT - 12-barrel kit | F30: OPA 90 Kit | H30: Stores | I30: Pending Approval | K30: To be Approved | L30: PCTC | M30: #N/A | N30: #N/A | O30: #N/A | P30: #N/A
A31: Glovis Luminous | C31: GLUM-60027/26 | D31: =IF(OR(ISNUMBER(SEARCH("Pre Delivery",E31)),ISNUMBER(SEARCH("Pre-Delivery",E31)),ISNUMBER(SEARCH("Predelivery",E31)),ISNUMBER(SEARCH("PD -",E31)),ISNUMBER(SEARCH("PD Lubes",E31))),"Pre-Delivery","") | E31: H.P machine - 2pcs (prefer Branded - Karcher/ KEW) | F31: High Pressure Washer | H31: Stores | I31: Pending Approval | K31: To be Approved | L31: PCTC | M31: #N/A | N31: #N/A | O31: #N/A | P31: #N/A
A32: Glovis Luminous | C32: GLUM-60028/26 | D32: =IF(OR(ISNUMBER(SEARCH("Pre Delivery",E32)),ISNUMBER(SEARCH("Pre-Delivery",E32)),ISNUMBER(SEARCH("Predelivery",E32)),ISNUMBER(SEARCH("PD -",E32)),ISNUMBER(SEARCH("PD Lubes",E32))),"Pre-Delivery","") | E32: Steam Splash Suit | F32: Steam Splash Suit | H32: Stores | I32: Pending Approval | K32: To be Approved | L32: PCTC | M32: #N/A | N32: #N/A | O32: #N/A | P32: #N/A
A33: Glovis Luminous | C33: GLUM-60033/26 | D33: =IF(OR(ISNUMBER(SEARCH("Pre Delivery",E33)),ISNUMBER(SEARCH("Pre-Delivery",E33)),ISNUMBER(SEARCH("Predelivery",E33)),ISNUMBER(SEARCH("PD -",E33)),ISNUMBER(SEARCH("PD Lubes",E33))),"Pre-Delivery","") | E33: Gas Meter | F33: Gas Meters | H33: Stores | L33: PCTC | M33: #N/A | N33: #N/A | O33: #N/A | P33: #N/A
A34: Glovis LightHouse | D34: =IF(OR(ISNUMBER(SEARCH("Pre Delivery",E34)),ISNUMBER(SEARCH("Pre-Delivery",E34)),ISNUMBER(SEARCH("Predelivery",E34)),ISNUMBER(SEARCH("PD -",E34)),ISNUMBER(SEARCH("PD Lubes",E34))),"Pre-Delivery","") | E34: Oily Water Separator | F34: Oily Water Separator | H34: Alfa Laval | L34: PCTC | M34: #N/A | N34: #N/A | O34: #N/A | P34: #N/A
A35: Glovis LightHouse | D35: =IF(OR(ISNUMBER(SEARCH("Pre Delivery",E35)),ISNUMBER(SEARCH("Pre-Delivery",E35)),ISNUMBER(SEARCH("Predelivery",E35)),ISNUMBER(SEARCH("PD -",E35)),ISNUMBER(SEARCH("PD Lubes",E35))),"Pre-Delivery","") | E35: BWTS Spares | F35: BWTS Spares | H35: Alfa Laval | L35: PCTC | M35: #N/A | N35: #N/A | O35: #N/A | P35: #N/A
A36: Glovis LightHouse | C36: GLIG-60094/26-1 | D36: =IF(OR(ISNUMBER(SEARCH("Pre Delivery",E36)),ISNUMBER(SEARCH("Pre-Delivery",E36)),ISNUMBER(SEARCH("Predelivery",E36)),ISNUMBER(SEARCH("PD -",E36)),ISNUMBER(SEARCH("PD Lubes",E36))),"Pre-Delivery","") | E36: EV Lance | F36: EV Lance | H36: Spares | L36: PCTC | M36: 1794590 | N36: JPY | O36: MOL Techno Trade Ltd | P36: Checking
A37: Glovis LightHouse | C37: GLIG-60034/26-1 | D37: =IF(OR(ISNUMBER(SEARCH("Pre Delivery",E37)),ISNUMBER(SEARCH("Pre-Delivery",E37)),ISNUMBER(SEARCH("Predelivery",E37)),ISNUMBER(SEARCH("PD -",E37)),ISNUMBER(SEARCH("PD Lubes",E37))),"Pre-Delivery","") | E37: Jonghap - PCTC Loose Fittings Procurement | F37: RO-RO Equipment - Loose Fittings | H37: Spares | L37: PCTC | M37: 486174 | N37: USD | O37: Jonghap Maritime Engineering Inc. | P37: Contracted
A38: Glovis LightHouse | C38: GLIG-60030/26-1 | D38: =IF(OR(ISNUMBER(SEARCH("Pre Delivery",E38)),ISNUMBER(SEARCH("Pre-Delivery",E38)),ISNUMBER(SEARCH("Predelivery",E38)),ISNUMBER(SEARCH("PD -",E38)),ISNUMBER(SEARCH("PD Lubes",E38))),"Pre-Delivery","") -> Pre-Delivery | E38: Pre Delivery Lubes Order# 3 (5714478288) | F38: Lubricants | H38: Lube Oil | L38: PCTC | M38: 305941 | N38: USD | O38: TotalEnergies Lubrifiants | P38: Contracted
A39: Glovis LightHouse | C39: GLIG-60021/26-1 | D39: =IF(OR(ISNUMBER(SEARCH("Pre Delivery",E39)),ISNUMBER(SEARCH("Pre-Delivery",E39)),ISNUMBER(SEARCH("Predelivery",E39)),ISNUMBER(SEARCH("PD -",E39)),ISNUMBER(SEARCH("PD Lubes",E39))),"Pre-Delivery","") | E39: FS-Interface-Light house | F39: IT Equipment - Interface / Integration | H39: Others | L39: PCTC | M39: 260191 | N39: HKD | O39: Interface Computer System Co. Ltd. | P39: Checking
A40: Glovis LightHouse | C40: GLIG-60005/26-1 | D40: =IF(OR(ISNUMBER(SEARCH("Pre Delivery",E40)),ISNUMBER(SEARCH("Pre-Delivery",E40)),ISNUMBER(SEARCH("Predelivery",E40)),ISNUMBER(SEARCH("PD -",E40)),ISNUMBER(SEARCH("PD Lubes",E40))),"Pre-Delivery","") | E40: Shipyard Extra Owner supply - Captains Eye | F40: Navigation - Captains Eye | H40: Spares | L40: PCTC | M40: 224200 | N40: USD | O40: Captain's Eye | P40: Contracted
A41: Glovis LightHouse | C41: GLIG-60079/26-1 | D41: =IF(OR(ISNUMBER(SEARCH("Pre Delivery",E41)),ISNUMBER(SEARCH("Pre-Delivery",E41)),ISNUMBER(SEARCH("Predelivery",E41)),ISNUMBER(SEARCH("PD -",E41)),ISNUMBER(SEARCH("PD Lubes",E41))),"Pre-Delivery","") | E41: Main Engine Spares | F41: Engine Spares - Main Engine | H41: Spares | L41: PCTC | M41: 215083 | N41: EUR | O41: MAN B and W Diesel-Copenhagen Denmark | P41: Checking
A42: Glovis LightHouse | C42: GLIG-60080/26-1 | D42: =IF(OR(ISNUMBER(SEARCH("Pre Delivery",E42)),ISNUMBER(SEARCH("Pre-Delivery",E42)),ISNUMBER(SEARCH("Predelivery",E42)),ISNUMBER(SEARCH("PD -",E42)),ISNUMBER(SEARCH("PD Lubes",E42))),"Pre-Delivery","") | E42: Aux. Engine Spares | F42: Engine Spares - Auxiliary Engine | H42: Spares | L42: PCTC | M42: 113839 | N42: EUR | O42: Wartsila Canada Inc. | P42: Checking
A43: Glovis LightHouse | D43: =IF(OR(ISNUMBER(SEARCH("Pre Delivery",E43)),ISNUMBER(SEARCH("Pre-Delivery",E43)),ISNUMBER(SEARCH("Predelivery",E43)),ISNUMBER(SEARCH("PD -",E43)),ISNUMBER(SEARCH("PD Lubes",E43))),"Pre-Delivery","") | E43: Sewage Traetment Plant | F43: Sewage Treatment Plant | H43: CSSC Nanjing | L43: PCTC | M43: #N/A | N43: #N/A | O43: #N/A | P43: #N/A
A44: Glovis LightHouse | D44: =IF(OR(ISNUMBER(SEARCH("Pre Delivery",E44)),ISNUMBER(SEARCH("Pre-Delivery",E44)),ISNUMBER(SEARCH("Predelivery",E44)),ISNUMBER(SEARCH("PD -",E44)),ISNUMBER(SEARCH("PD Lubes",E44))),"Pre-Delivery","") | E44: Sewage Discharge P/P | F44: Sewage Discharge Pump | H44: CSSC Nanjing | L44: PCTC | M44: #N/A | N44: #N/A | O44: #N/A | P44: #N/A
A45: Glovis LightHouse | C45: GLIG-60002/25-1 | D45: =IF(OR(ISNUMBER(SEARCH("Pre Delivery",E45)),ISNUMBER(SEARCH("Pre-Delivery",E45)),ISNUMBER(SEARCH("Predelivery",E45)),ISNUMBER(SEARCH("PD -",E45)),ISNUMBER(SEARCH("PD Lubes",E45))),"Pre-Delivery","") -> Pre-Delivery | E45: Pre-Delivery - Lubes | F45: Lubricants | H45: Lube Oil | L45: PCTC | M45: 83443 | N45: USD | O45: TotalEnergies Lubrifiants | P45: Contracted
A46: Glovis LightHouse | C46: GLIG-60076/26-1 | D46: =IF(OR(ISNUMBER(SEARCH("Pre Delivery",E46)),ISNUMBER(SEARCH("Pre-Delivery",E46)),ISNUMBER(SEARCH("Predelivery",E46)),ISNUMBER(SEARCH("PD -",E46)),ISNUMBER(SEARCH("PD Lubes",E46))),"Pre-Delivery","") | E46: Steam Splash Suit | F46: Steam Splash Suit | H46: Stores | L46: PCTC | M46: 83000 | N46: INR | O46: Shiva Enterprises | P46: Checking
A47: Glovis LightHouse | C47: GLIG-60066/26-1 | D47: =IF(OR(ISNUMBER(SEARCH("Pre Delivery",E47)),ISNUMBER(SEARCH("Pre-Delivery",E47)),ISNUMBER(SEARCH("Predelivery",E47)),ISNUMBER(SEARCH("PD -",E47)),ISNUMBER(SEARCH("PD Lubes",E47))),"Pre-Delivery","") | E47: Mooring Rope | F47: Mooring Ropes | H47: Spares | L47: PCTC | M47: 80788 | N47: USD | O47: XINGLUN ROPE CABLE CO.,LTD | P47: Contracted
A48: Glovis LightHouse | C48: GLIG-60024/26-1 | D48: =IF(OR(ISNUMBER(SEARCH("Pre Delivery",E48)),ISNUMBER(SEARCH("Pre-Delivery",E48)),ISNUMBER(SEARCH("Predelivery",E48)),ISNUMBER(SEARCH("PD -",E48)),ISNUMBER(SEARCH("PD Lubes",E48))),"Pre-Delivery","") | E48: Shipyard Extra Buyer Supply - HiNAS SVM 10800 A-Q-2025-09-02_R0 | F48: Navigation - HiNAS SVM | H48: Spares | L48: PCTC | M48: 63600 | N48: USD | O48: Avikus Co., Ltd. | P48: Contracted
A49: Glovis LightHouse | C49: GLIG-60003/26-1 | D49: =IF(OR(ISNUMBER(SEARCH("Pre Delivery",E49)),ISNUMBER(SEARCH("Pre-Delivery",E49)),ISNUMBER(SEARCH("Predelivery",E49)),ISNUMBER(SEARCH("PD -",E49)),ISNUMBER(SEARCH("PD Lubes",E49))),"Pre-Delivery","") | E49: Interface PO | F49: IT Equipment - Interface / Integration | H49: Others | L49: PCTC | M49: 55710 | N49: HKD | O49: Interface Computer System Co. Ltd. | P49: Checking
A50: Glovis LightHouse | D50: =IF(OR(ISNUMBER(SEARCH("Pre Delivery",E50)),ISNUMBER(SEARCH("Pre-Delivery",E50)),ISNUMBER(SEARCH("Predelivery",E50)),ISNUMBER(SEARCH("PD -",E50)),ISNUMBER(SEARCH("PD Lubes",E50))),"Pre-Delivery","") | E50: RSC Lube oil - qty / Total for Glovis Lighthouse | F50: Lubricants | H50: Lube Oil | L50: PCTC | M50: #N/A | N50: #N/A | O50: #N/A | P50: #N/A
A51: Glovis LightHouse | C51: GLIG-60001/25-1 | D51: =IF(OR(ISNUMBER(SEARCH("Pre Delivery",E51)),ISNUMBER(SEARCH("Pre-Delivery",E51)),ISNUMBER(SEARCH("Predelivery",E51)),ISNUMBER(SEARCH("PD -",E51)),ISNUMBER(SEARCH("PD Lubes",E51))),"Pre-Delivery","") -> Pre-Delivery | E51: Lubricants - Pre Delivery | F51: Lubricants | H51: Lube Oil | L51: PCTC | M51: 51230 | N51: USD | O51: TotalEnergies Lubrifiants | P51: Contracted
A52: Glovis LightHouse | C52: GLIG-60022/26-1 | D52: =IF(OR(ISNUMBER(SEARCH("Pre Delivery",E52)),ISNUMBER(SEARCH("Pre-Delivery",E52)),ISNUMBER(SEARCH("Predelivery",E52)),ISNUMBER(SEARCH("PD -",E52)),ISNUMBER(SEARCH("PD Lubes",E52))),"Pre-Delivery","") | E52: FS-LENOVO-Lighthouse | F52: IT Equipment - Computers (Lenovo) | H52: Others | L52: PCTC | M52: 49419 | N52: CAD | O52: IT Blueprint Solutions Consulting Inc | P52: Checking
A53: Glovis LightHouse | C53: GLIG-60087/26-1 | D53: =IF(OR(ISNUMBER(SEARCH("Pre Delivery",E53)),ISNUMBER(SEARCH("Pre-Delivery",E53)),ISNUMBER(SEARCH("Predelivery",E53)),ISNUMBER(SEARCH("PD -",E53)),ISNUMBER(SEARCH("PD Lubes",E53))),"Pre-Delivery","") | E53: Buyer Supply - 10,800 PCTC Citadel VHF/GPS and UHF ANTENNA system | F53: Citadel VHF/GPS/UHF System | H53: Spares | L53: PCTC | M53: 39000 | N53: USD | O53: West Nautical Pte Ltd | P53: Contracted
A54: Glovis LightHouse | C54: GLIG-60100/26-1 | D54: =IF(OR(ISNUMBER(SEARCH("Pre Delivery",E54)),ISNUMBER(SEARCH("Pre-Delivery",E54)),ISNUMBER(SEARCH("Predelivery",E54)),ISNUMBER(SEARCH("PD -",E54)),ISNUMBER(SEARCH("PD Lubes",E54))),"Pre-Delivery","") | E54: UHF Radio (Handheld) | F54: UHF Radio | H54: Spares | L54: PCTC | M54: 32128 | N54: USD | O54: Vessel Link Marine Supply & Service Ltd | P54: Contracted
A55: Glovis LightHouse | C55: GLIG-60078/26-1 | D55: =IF(OR(ISNUMBER(SEARCH("Pre Delivery",E55)),ISNUMBER(SEARCH("Pre-Delivery",E55)),ISNUMBER(SEARCH("Predelivery",E55)),ISNUMBER(SEARCH("PD -",E55)),ISNUMBER(SEARCH("PD Lubes",E55))),"Pre-Delivery","") -> Pre-Delivery | E55: Pre Delivery - Welding Equipment | F55: Welding Equipment | H55: Chemicals | L55: PCTC | M55: 30943 | N55: USD | O55: Drew Marine USA, Inc | P55: Contracted
A56: Glovis LightHouse | C56: GLIG-60096/26-1 | D56: =IF(OR(ISNUMBER(SEARCH("Pre Delivery",E56)),ISNUMBER(SEARCH("Pre-Delivery",E56)),ISNUMBER(SEARCH("Predelivery",E56)),ISNUMBER(SEARCH("PD -",E56)),ISNUMBER(SEARCH("PD Lubes",E56))),"Pre-Delivery","") | E56: Final Sailing Qty of Lubes | F56: Lubricants | H56: Lube Oil | L56: PCTC | M56: 30700 | N56: USD | O56: TotalEnergies Lubrifiants | P56: Contracted
A57: Glovis LightHouse | C57: GLIG-60012/26-1 | D57: =IF(OR(ISNUMBER(SEARCH("Pre Delivery",E57)),ISNUMBER(SEARCH("Pre-Delivery",E57)),ISNUMBER(SEARCH("Predelivery",E57)),ISNUMBER(SEARCH("PD -",E57)),ISNUMBER(SEARCH("PD Lubes",E57))),"Pre-Delivery","") | E57: FS-ITBP -glovis lighthouse | F57: IT Equipment - ITBP | H57: Others | L57: PCTC | M57: 29716 | N57: USD | O57: IT Blueprint Solutions Consulting Inc | P57: Contracted
A58: Glovis LightHouse | C58: GLIG-60037/26-1 | D58: =IF(OR(ISNUMBER(SEARCH("Pre Delivery",E58)),ISNUMBER(SEARCH("Pre-Delivery",E58)),ISNUMBER(SEARCH("Predelivery",E58)),ISNUMBER(SEARCH("PD -",E58)),ISNUMBER(SEARCH("PD Lubes",E58))),"Pre-Delivery","") | E58: Reliabiltiy Spares - Gas Detection System | F58: Gas Detection System | H58: Spares | L58: PCTC | M58: 28136 | N58: USD | O58: Consilium Marine and Safety Canada | P58: Contracted
A59: Glovis LightHouse | C59: GLIG-60010/26-1 | D59: =IF(OR(ISNUMBER(SEARCH("Pre Delivery",E59)),ISNUMBER(SEARCH("Pre-Delivery",E59)),ISNUMBER(SEARCH("Predelivery",E59)),ISNUMBER(SEARCH("PD -",E59)),ISNUMBER(SEARCH("PD Lubes",E59))),"Pre-Delivery","") | E59: FS-VLINK-H1610 | F59: Communications - VLINK | H59: Others | L59: PCTC | M59: 25285 | N59: USD | O59: Vessel Link Marine Supply & Service Ltd | P59: Contracted
A60: Glovis LightHouse | C60: GLIG-60033/26-1 | D60: =IF(OR(ISNUMBER(SEARCH("Pre Delivery",E60)),ISNUMBER(SEARCH("Pre-Delivery",E60)),ISNUMBER(SEARCH("Predelivery",E60)),ISNUMBER(SEARCH("PD -",E60)),ISNUMBER(SEARCH("PD Lubes",E60))),"Pre-Delivery","") | E60: Reliability Spares - PCTC-Seaspan - Boilers QUOT26012103 | F60: Boiler Spares | H60: Spares | L60: PCTC | M60: 23968 | N60: USD | O60: Kangrim Industries Company Limited | P60: Contracted
A61: Glovis LightHouse | C61: GLIG-60067/26-1 | D61: =IF(OR(ISNUMBER(SEARCH("Pre Delivery",E61)),ISNUMBER(SEARCH("Pre-Delivery",E61)),ISNUMBER(SEARCH("Predelivery",E61)),ISNUMBER(SEARCH("PD -",E61)),ISNUMBER(SEARCH("PD Lubes",E61))),"Pre-Delivery","") | E61: Service: LNG OPERATION MANUAL Development | F61: LNG Operation Manual | H61: Others | L61: PCTC | M61: 21500 | N61: USD | O61: VMT Co., Ltd | P61: Contracted
A62: Glovis LightHouse | C62: GLIG-60075/26-1 | D62: =IF(OR(ISNUMBER(SEARCH("Pre Delivery",E62)),ISNUMBER(SEARCH("Pre-Delivery",E62)),ISNUMBER(SEARCH("Predelivery",E62)),ISNUMBER(SEARCH("PD -",E62)),ISNUMBER(SEARCH("PD Lubes",E62))),"Pre-Delivery","") -> Pre-Delivery | E62: Pre Delivery - Engineering Products & Kits (DREW) | F62: Engineering Products & Chemicals | H62: Chemicals | L62: PCTC | M62: 20709 | N62: USD | O62: Drew Marine USA, Inc | P62: Contracted
... A68: Glovis LightHouse | C68: GLIG-60047/26-1 | D68: =IF(OR(ISNUMBER(SEARCH("Pre Delivery",E68)),ISNUMBER(SEARCH("Pre-Delivery",E68)),ISNUMBER(SEARCH("Predelivery",E68)),ISNUMBER(SEARCH("PD -",E68)),ISNUMBER(SEARCH("PD Lubes",E68))),"Pre-Delivery","") -> Pre-Delivery | E68: Pre Delivery - Sample Cooler | F68: Sample Cooler | H68: Spares | L68: PCTC | M68: 10858 | N68: USD | O68: Drew Marine USA, Inc | P68: Contracted
A69: Glovis LightHouse | C69: GLIG-60020/26 | D69: =IF(OR(ISNUMBER(SEARCH("Pre Delivery",E69)),ISNUMBER(SEARCH("Pre-Delivery",E69)),ISNUMBER(SEARCH("Predelivery",E69)),ISNUMBER(SEARCH("PD -",E69)),ISNUMBER(SEARCH("PD Lubes",E69))),"Pre-Delivery","") | E69: Interface -equipment-lighthouse | F69: IT Equipment - Interface / Integration | H69: Others | L69: PCTC | M69: #N/A | N69: #N/A | O69: #N/A | P69: #N/A
A70: Glovis LightHouse | C70: GLIG-60018/26 | D70: =IF(OR(ISNUMBER(SEARCH("Pre Delivery",E70)),ISNUMBER(SEARCH("Pre-Delivery",E70)),ISNUMBER(SEARCH("Predelivery",E70)),ISNUMBER(SEARCH("PD -",E70)),ISNUMBER(SEARCH("PD Lubes",E70))),"Pre-Delivery","") | E70: FS-KVH-LIGHTHOUSE | F70: Communications - VSAT (KVH) | H70: Others | L70: PCTC | M70: #N/A | N70: #N/A | O70: #N/A | P70: #N/A
A71: Glovis LightHouse | C71: GLIG-60016/26 | D71: =IF(OR(ISNUMBER(SEARCH("Pre Delivery",E71)),ISNUMBER(SEARCH("Pre-Delivery",E71)),ISNUMBER(SEARCH("Predelivery",E71)),ISNUMBER(SEARCH("PD -",E71)),ISNUMBER(SEARCH("PD Lubes",E71))),"Pre-Delivery","") | E71: Sihui Marine-light house | F71: IT Equipment - Sihui Marine | H71: Others | L71: PCTC | M71: #N/A | N71: #N/A | O71: #N/A | P71: #N/A
A72: Glovis LightHouse | C72: GLIG-60014/26 | D72: =IF(OR(ISNUMBER(SEARCH("Pre Delivery",E72)),ISNUMBER(SEARCH("Pre-Delivery",E72)),ISNUMBER(SEARCH("Predelivery",E72)),ISNUMBER(SEARCH("PD -",E72)),ISNUMBER(SEARCH("PD Lubes",E72))),"Pre-Delivery","") | E72: FS-X10 | F72: IT Equipment - X10 System | H72: Others | L72: PCTC | M72: #N/A | N72: #N/A | O72: #N/A | P72: #N/A
A73: Glovis LightHouse | C73: GLIG-60009/26 | D73: =IF(OR(ISNUMBER(SEARCH("Pre Delivery",E73)),ISNUMBER(SEARCH("Pre-Delivery",E73)),ISNUMBER(SEARCH("Predelivery",E73)),ISNUMBER(SEARCH("PD -",E73)),ISNUMBER(SEARCH("PD Lubes",E73))),"Pre-Delivery","") | E73: FS-ITBP -1 | F73: IT Equipment - ITBP | H73: Others | L73: PCTC | M73: #N/A | N73: #N/A | O73: #N/A | P73: #N/A
A74: Glovis LightHouse | C74: GLIG-60007/25 | D74: =IF(OR(ISNUMBER(SEARCH("Pre Delivery",E74)),ISNUMBER(SEARCH("Pre-Delivery",E74)),ISNUMBER(SEARCH("Predelivery",E74)),ISNUMBER(SEARCH("PD -",E74)),ISNUMBER(SEARCH("PD Lubes",E74))),"Pre-Delivery","") | E74: FS services | F74: Fleet Systems - Services | H74: Others | L74: PCTC | M74: #N/A | N74: #N/A | O74: #N/A | P74: #N/A
A75: Glovis LightHouse | C75: GLIG-60040/26-1 | D75: =IF(OR(ISNUMBER(SEARCH("Pre Delivery",E75)),ISNUMBER(SEARCH("Pre-Delivery",E75)),ISNUMBER(SEARCH("Predelivery",E75)),ISNUMBER(SEARCH("PD -",E75)),ISNUMBER(SEARCH("PD Lubes",E75))),"Pre-Delivery","") | E75: FS-VLINK-Starlink Accessories | F75: Communications - Starlink Accessories | H75: Others | L75: PCTC | M75: #N/A | N75: #N/A | O75: #N/A | P75: #N/A
A76: Glovis LightHouse | C76: GLIG-60002/26 | D76: =IF(OR(ISNUMBER(SEARCH("Pre Delivery",E76)),ISNUMBER(SEARCH("Pre-Delivery",E76)),ISNUMBER(SEARCH("Predelivery",E76)),ISNUMBER(SEARCH("PD -",E76)),ISNUMBER(SEARCH("PD Lubes",E76))),"Pre-Delivery","") | E76: fs interface | F76: IT Equipment - Interface / Integration | H76: Others | L76: PCTC | M76: #N/A | N76: #N/A | O76: #N/A | P76: #N/A
A77: Glovis LightHouse | C77: GLIG-60032/26 | D77: =IF(OR(ISNUMBER(SEARCH("Pre Delivery",E77)),ISNUMBER(SEARCH("Pre-Delivery",E77)),ISNUMBER(SEARCH("Predelivery",E77)),ISNUMBER(SEARCH("PD -",E77)),ISNUMBER(SEARCH("PD Lubes",E77))),"Pre-Delivery","") | E77: FS-ITBP-LICENSES | F77: IT Equipment - ITBP Licenses | H77: Others | L77: PCTC | M77: #N/A | N77: #N/A | O77: #N/A | P77: #N/A
A78: Glovis LightHouse | C78: GLIG-60001/26 | D78: =IF(OR(ISNUMBER(SEARCH("Pre Delivery",E78)),ISNUMBER(SEARCH("Pre-Delivery",E78)),ISNUMBER(SEARCH("Predelivery",E78)),ISNUMBER(SEARCH("PD -",E78)),ISNUMBER(SEARCH("PD Lubes",E78))),"Pre-Delivery","") | E78: FS | F78: Fleet Systems - General | H78: Others | L78: PCTC | M78: #N/A | N78: #N/A | O78: #N/A | P78: #N/A
A79: Glovis LightHouse | C79: GLIG-60081/26 | D79: =IF(OR(ISNUMBER(SEARCH("Pre Delivery",E79)),ISNUMBER(SEARCH("Pre-Delivery",E79)),ISNUMBER(SEARCH("Predelivery",E79)),ISNUMBER(SEARCH("PD -",E79)),ISNUMBER(SEARCH("PD Lubes",E79))),"Pre-Delivery","") | E79: FS-ITBP tax invoice | F79: IT Equipment - ITBP Tax Invoice | H79: Others | L79: PCTC | M79: #N/A | N79: #N/A | O79: #N/A | P79: #N/A
A80: Glovis LightHouse | C80: GLIG-60082/26 | D80: =IF(OR(ISNUMBER(SEARCH("Pre Delivery",E80)),ISNUMBER(SEARCH("Pre-Delivery",E80)),ISNUMBER(SEARCH("Predelivery",E80)),ISNUMBER(SEARCH("PD -",E80)),ISNUMBER(SEARCH("PD Lubes",E80))),"Pre-Delivery","") | E80: fs-x10 sample test | F80: IT Equipment - X10 System | H80: Others | L80: PCTC | M80: #N/A | N80: #N/A | O80: #N/A | P80: #N/A
A81: Glovis LightHouse | C81: GLIG-60042/26-1 | D81: =IF(OR(ISNUMBER(SEARCH("Pre Delivery",E81)),ISNUMBER(SEARCH("Pre-Delivery",E81)),ISNUMBER(SEARCH("Predelivery",E81)),ISNUMBER(SEARCH("PD -",E81)),ISNUMBER(SEARCH("PD Lubes",E81))),"Pre-Delivery","") | E81: SHIPYARD EXTRA OWNER SUPPLY- Abanaki Skimmers | F81: Oil Skimmers - Abanaki | H81: Spares | L81: PCTC | M81: 10325 | N81: USD | O81: Hermont Marine Inc | P81: Contracted
A82: Glovis LightHouse | C82: GLIG-60038/26-1 | D82: =IF(OR(ISNUMBER(SEARCH("Pre Delivery",E82)),ISNUMBER(SEARCH("Pre-Delivery",E82)),ISNUMBER(SEARCH("Predelivery",E82)),ISNUMBER(SEARCH("PD -",E82)),ISNUMBER(SEARCH("PD Lubes",E82))),"Pre-Delivery","") | E82: Reliability Spares - Fire detection system | F82: Fire Detection System | H82: Spares | L82: PCTC | M82: 9933 | N82: USD | O82: Consilium Marine and Safety Canada | P82: Contracted
A83: Glovis LightHouse | C83: GLIG-60068/26-1 | D83: =IF(OR(ISNUMBER(SEARCH("Pre Delivery",E83)),ISNUMBER(SEARCH("Pre-Delivery",E83)),ISNUMBER(SEARCH("Predelivery",E83)),ISNUMBER(SEARCH("PD -",E83)),ISNUMBER(SEARCH("PD Lubes",E83))),"Pre-Delivery","") -> Pre-Delivery | E83: Pre Delivery - Treatment Chemical | F83: Treatment Chemicals | H83: Chemicals | L83: PCTC | M83: 9266 | N83: USD | O83: Drew Marine USA, Inc | P83: Contracted
A84: Glovis LightHouse | C84: GLIG-60092/26-1 | D84: =IF(OR(ISNUMBER(SEARCH("Pre Delivery",E84)),ISNUMBER(SEARCH("Pre-Delivery",E84)),ISNUMBER(SEARCH("Predelivery",E84)),ISNUMBER(SEARCH("PD -",E84)),ISNUMBER(SEARCH("PD Lubes",E84))),"Pre-Delivery","") | E84: Publications | F84: Publications & Manuals | H84: Stores | L84: PCTC | M84: 9105 | N84: USD | O84: Yinxiang Industrial HK Co Limited | P84: Contracted
A85: Glovis LightHouse | C85: GLIG-60071/26-1 | D85: =IF(OR(ISNUMBER(SEARCH("Pre Delivery",E85)),ISNUMBER(SEARCH("Pre-Delivery",E85)),ISNUMBER(SEARCH("Predelivery",E85)),ISNUMBER(SEARCH("PD -",E85)),ISNUMBER(SEARCH("PD Lubes",E85))),"Pre-Delivery","") | E85: Refrigerant Equipment | F85: Refrigerant Equipment | H85: Chemicals | L85: PCTC | M85: 7740 | N85: USD | O85: Drew Marine USA, Inc | P85: Contracted
A86: Glovis LightHouse | C86: GLIG-60048/26-1 | D86: =IF(OR(ISNUMBER(SEARCH("Pre Delivery",E86)),ISNUMBER(SEARCH("Pre-Delivery",E86)),ISNUMBER(SEARCH("Predelivery",E86)),ISNUMBER(SEARCH("PD -",E86)),ISNUMBER(SEARCH("PD Lubes",E86))),"Pre-Delivery","") | E86: Reliability - Donghwa Spares for BOG Compressor | F86: BOG Compressor Spares | H86: Spares | L86: PCTC | M86: 7060 | N86: USD | O86: DONGHWA ENTEC CO. ,LTD | P86: Contracted
A87: Glovis LightHouse | C87: GLIG-60103/26-1 | D87: =IF(OR(ISNUMBER(SEARCH("Pre Delivery",E87)),ISNUMBER(SEARCH("Pre-Delivery",E87)),ISNUMBER(SEARCH("Predelivery",E87)),ISNUMBER(SEARCH("PD -",E87)),ISNUMBER(SEARCH("PD Lubes",E87))),"Pre-Delivery","") | E87: IMPA Stores - BA Compressor | F87: IMPA Stores - BA Compressor | H87: Stores | L87: PCTC | M87: 6929 | N87: USD | O87: Dan Marine Group Ltd. | P87: Contracted
A88: Glovis LightHouse | C88: GLIG-60019/26-1 | D88: =IF(OR(ISNUMBER(SEARCH("Pre Delivery",E88)),ISNUMBER(SEARCH("Pre-Delivery",E88)),ISNUMBER(SEARCH("Predelivery",E88)),ISNUMBER(SEARCH("PD -",E88)),ISNUMBER(SEARCH("PD Lubes",E88))),"Pre-Delivery","") | E88: FS-KVH -LIGHTHOUSE UPDATED | F88: Communications - VSAT (KVH) | H88: Others | L88: PCTC | M88: 6775 | N88: USD | O88: KVH Industries Inc | P88: Contracted
A89: Glovis LightHouse | C89: GLIG-60060/26-1 | D89: =IF(OR(ISNUMBER(SEARCH("Pre Delivery",E89)),ISNUMBER(SEARCH("Pre-Delivery",E89)),ISNUMBER(SEARCH("Predelivery",E89)),ISNUMBER(SEARCH("PD -",E89)),ISNUMBER(SEARCH("PD Lubes",E89))),"Pre-Delivery","") | E89: IMPA Stores - Engine | F89: IMPA Stores - Engine | H89: Stores | L89: PCTC | M89: 6363 | N89: USD | O89: Fuji Marine Logistics Shunyang(Shanghai) Co., LIMITED | P89: Contracted
A90: Glovis LightHouse | C90: GLIG-60063/26-1 | D90: =IF(OR(ISNUMBER(SEARCH("Pre Delivery",E90)),ISNUMBER(SEARCH("Pre-Delivery",E90)),ISNUMBER(SEARCH("Predelivery",E90)),ISNUMBER(SEARCH("PD -",E90)),ISNUMBER(SEARCH("PD Lubes",E90))),"Pre-Delivery","") | E90: IMPA Stores - Engine | F90: IMPA Stores - Engine | H90: Stores | L90: PCTC | M90: 6224 | N90: USD | O90: Fuji Marine Logistics Shunyang(Shanghai) Co., LIMITED | P90: Contracted
A91: Glovis LightHouse | C91: GLIG-60102/26-1 | D91: =IF(OR(ISNUMBER(SEARCH("Pre Delivery",E91)),ISNUMBER(SEARCH("Pre-Delivery",E91)),ISNUMBER(SEARCH("Predelivery",E91)),ISNUMBER(SEARCH("PD -",E91)),ISNUMBER(SEARCH("PD Lubes",E91))),"Pre-Delivery","") | E91: Temperature Calibrators | F91: Temperature Calibrators | H91: Stores | L91: PCTC | M91: 5860 | N91: USD | O91: Dan Marine Group Ltd. | P91: Contracted
A92: Glovis LightHouse | C92: GLIG-60102/26-1 | D92: =IF(OR(ISNUMBER(SEARCH("Pre Delivery",E92)),ISNUMBER(SEARCH("Pre-Delivery",E92)),ISNUMBER(SEARCH("Predelivery",E92)),ISNUMBER(SEARCH("PD -",E92)),ISNUMBER(SEARCH("PD Lubes",E92))),"Pre-Delivery","") | E92: Pressure Calibrators | F92: Pressure Calibrators | H92: Stores | L92: PCTC | M92: 5860 | N92: USD | O92: Dan Marine Group Ltd. | P92: Contracted
... A101: Glovis LightHouse | C101: GLIG-60015/26-1 | D101: =IF(OR(ISNUMBER(SEARCH("Pre Delivery",E101)),ISNUMBER(SEARCH("Pre-Delivery",E101)),ISNUMBER(SEARCH("Predelivery",E101)),ISNUMBER(SEARCH("PD -",E101)),ISNUMBER(SEARCH("PD Lubes",E101))),"Pre-Delivery","") | E101: FS-X10 | F101: IT Equipment - X10 System | H101: Others | L101: PCTC | M101: 4281 | N101: CAD | O101: X10 Networks Inc. | P101: Checking
A102: Glovis LightHouse | C102: GLIG-60097/26-1 | D102: =IF(OR(ISNUMBER(SEARCH("Pre Delivery",E102)),ISNUMBER(SEARCH("Pre-Delivery",E102)),ISNUMBER(SEARCH("Predelivery",E102)),ISNUMBER(SEARCH("PD -",E102)),ISNUMBER(SEARCH("PD Lubes",E102))),"Pre-Delivery","") | H102: Others | L102: PCTC | M102: 4040 | N102: USD | O102: KVH Industries Inc | P102: Contracted
A103: Glovis LightHouse | C103: GLIG-60003/25 | D103: =IF(OR(ISNUMBER(SEARCH("Pre Delivery",E103)),ISNUMBER(SEARCH("Pre-Delivery",E103)),ISNUMBER(SEARCH("Predelivery",E103)),ISNUMBER(SEARCH("PD -",E103)),ISNUMBER(SEARCH("PD Lubes",E103))),"Pre-Delivery","") | E103: Citadel VHF/GPS and UHF ANTENNA system | F103: Citadel VHF/GPS/UHF System | H103: Spares | L103: PCTC | M103: #N/A | N103: #N/A | O103: #N/A | P103: #N/A
A104: Glovis LightHouse | C104: GLIG-60085/26-1 | D104: =IF(OR(ISNUMBER(SEARCH("Pre Delivery",E104)),ISNUMBER(SEARCH("Pre-Delivery",E104)),ISNUMBER(SEARCH("Predelivery",E104)),ISNUMBER(SEARCH("PD -",E104)),ISNUMBER(SEARCH("PD Lubes",E104))),"Pre-Delivery","") | E104: Air driven HP Pump - For hydraulic nuts for M/E | F104: HP Pump (Hydraulic Nuts) | H104: Spares | L104: PCTC | M104: #N/A | N104: #N/A | O104: #N/A | P104: #N/A
A105: Glovis LightHouse | D105: =IF(OR(ISNUMBER(SEARCH("Pre Delivery",E105)),ISNUMBER(SEARCH("Pre-Delivery",E105)),ISNUMBER(SEARCH("Predelivery",E105)),ISNUMBER(SEARCH("PD -",E105)),ISNUMBER(SEARCH("PD Lubes",E105))),"Pre-Delivery","") | E105: Reliability RO-RO Equipment (Main & Centre Ramp spares + inner Ramp spares) | F105: RO-RO Equipment - Ramp Spares | H105: Spares | L105: PCTC | M105: #N/A | N105: #N/A | O105: #N/A | P105: #N/A
A106: Glovis LightHouse | D106: =IF(OR(ISNUMBER(SEARCH("Pre Delivery",E106)),ISNUMBER(SEARCH("Pre-Delivery",E106)),ISNUMBER(SEARCH("Predelivery",E106)),ISNUMBER(SEARCH("PD -",E106)),ISNUMBER(SEARCH("PD Lubes",E106))),"Pre-Delivery","") | E106: Reliability HP Pump Skid | F106: HP Pump Skid | H106: Spares | L106: PCTC | M106: #N/A | N106: #N/A | O106: #N/A | P106: #N/A
A107: Glovis LightHouse | D107: =IF(OR(ISNUMBER(SEARCH("Pre Delivery",E107)),ISNUMBER(SEARCH("Pre-Delivery",E107)),ISNUMBER(SEARCH("Predelivery",E107)),ISNUMBER(SEARCH("PD -",E107)),ISNUMBER(SEARCH("PD Lubes",E107))),"Pre-Delivery","") | E107: Reefer cable and plugs extensions | F107: Reefer Cables & Plugs | H107: Spares | L107: PCTC | M107: #N/A | N107: #N/A | O107: #N/A | P107: #N/A
A108: Glovis LightHouse | C108: GLIG-60115/26 | D108: =IF(OR(ISNUMBER(SEARCH("Pre Delivery",E108)),ISNUMBER(SEARCH("Pre-Delivery",E108)),ISNUMBER(SEARCH("Predelivery",E108)),ISNUMBER(SEARCH("PD -",E108)),ISNUMBER(SEARCH("PD Lubes",E108))),"Pre-Delivery","") | E108: Gas Cylinders | F108: Gas Cylinders | H108: Spares | L108: PCTC | M108: #N/A | N108: #N/A | O108: #N/A | P108: #N/A
A109: Glovis LightHouse | D109: =IF(OR(ISNUMBER(SEARCH("Pre Delivery",E109)),ISNUMBER(SEARCH("Pre-Delivery",E109)),ISNUMBER(SEARCH("Predelivery",E109)),ISNUMBER(SEARCH("PD -",E109)),ISNUMBER(SEARCH("PD Lubes",E109))),"Pre-Delivery","") | E109: Thermal Stop PO | F109: Thermal Stop | H109: Spares | L109: PCTC | M109: #N/A | N109: #N/A | O109: #N/A | P109: #N/A
A110: Glovis LightHouse | D110: =IF(OR(ISNUMBER(SEARCH("Pre Delivery",E110)),ISNUMBER(SEARCH("Pre-Delivery",E110)),ISNUMBER(SEARCH("Predelivery",E110)),ISNUMBER(SEARCH("PD -",E110)),ISNUMBER(SEARCH("PD Lubes",E110))),"Pre-Delivery","") | E110: Receptacles | F110: Receptacles | H110: Spares | L110: PCTC | M110: #N/A | N110: #N/A | O110: #N/A | P110: #N/A
A111: Glovis LightHouse | D111: =IF(OR(ISNUMBER(SEARCH("Pre Delivery",E111)),ISNUMBER(SEARCH("Pre-Delivery",E111)),ISNUMBER(SEARCH("Predelivery",E111)),ISNUMBER(SEARCH("PD -",E111)),ISNUMBER(SEARCH("PD Lubes",E111))),"Pre-Delivery","") | E111: Trelleborg Safe lanes | F111: Safe Lanes (Trelleborg) | H111: Spares | L111: PCTC | M111: #N/A | N111: #N/A | O111: #N/A | P111: #N/A
A112: Glovis LightHouse | C112: GLIG-60101/26 | D112: =IF(OR(ISNUMBER(SEARCH("Pre Delivery",E112)),ISNUMBER(SEARCH("Pre-Delivery",E112)),ISNUMBER(SEARCH("Predelivery",E112)),ISNUMBER(SEARCH("PD -",E112)),ISNUMBER(SEARCH("PD Lubes",E112))),"Pre-Delivery","") | E112: Main Engine - Additional Spares | F112: Engine Spares - Main Engine | H112: Spares | L112: PCTC | M112: #N/A | N112: #N/A | O112: #N/A | P112: #N/A
A113: Glovis LightHouse | C113: GLIG-60046/26-1 | D113: =IF(OR(ISNUMBER(SEARCH("Pre Delivery",E113)),ISNUMBER(SEARCH("Pre-Delivery",E113)),ISNUMBER(SEARCH("Predelivery",E113)),ISNUMBER(SEARCH("PD -",E113)),ISNUMBER(SEARCH("PD Lubes",E113))),"Pre-Delivery","") | E113: Seatab | F113: Seatab | H113: Spares | L113: PCTC | M113: 3887 | N113: USD | O113: OneOcean AS | P113: Contracted
A114: Glovis LightHouse | C114: GLIG-60073/26-1 | D114: =IF(OR(ISNUMBER(SEARCH("Pre Delivery",E114)),ISNUMBER(SEARCH("Pre-Delivery",E114)),ISNUMBER(SEARCH("Predelivery",E114)),ISNUMBER(SEARCH("PD -",E114)),ISNUMBER(SEARCH("PD Lubes",E114))),"Pre-Delivery","") -> Pre-Delivery | E114: Pre-Delivery - OPA 90 | F114: OPA 90 Kit | H114: Stores | L114: PCTC | M114: 3400 | N114: USD | O114: Vessel Link Marine Supply & Service Ltd | P114: Contracted
A115: Glovis LightHouse | C115: GLIG-60077/26-1 | D115: =IF(OR(ISNUMBER(SEARCH("Pre Delivery",E115)),ISNUMBER(SEARCH("Pre-Delivery",E115)),ISNUMBER(SEARCH("Predelivery",E115)),ISNUMBER(SEARCH("PD -",E115)),ISNUMBER(SEARCH("PD Lubes",E115))),"Pre-Delivery","") | E115: Crew Care | F115: Crew Welfare | H115: Chemicals | L115: PCTC | M115: 3075 | N115: USD | O115: Drew Marine USA, Inc | P115: Contracted
A116: Glovis LightHouse | C116: GLIG-60050/26-1 | D116: =IF(OR(ISNUMBER(SEARCH("Pre Delivery",E116)),ISNUMBER(SEARCH("Pre-Delivery",E116)),ISNUMBER(SEARCH("Predelivery",E116)),ISNUMBER(SEARCH("PD -",E116)),ISNUMBER(SEARCH("PD Lubes",E116))),"Pre-Delivery","") | E116: IMPA Stores Stationery | F116: IMPA Stores - Stationery | H116: Stores | L116: PCTC | M116: 2698 | N116: USD | O116: RMS Marine Service Company Ltd. | P116: Contracted
A117: Glovis LightHouse | C117: GLIG-60026/26-2 | D117: =IF(OR(ISNUMBER(SEARCH("Pre Delivery",E117)),ISNUMBER(SEARCH("Pre-Delivery",E117)),ISNUMBER(SEARCH("Predelivery",E117)),ISNUMBER(SEARCH("PD -",E117)),ISNUMBER(SEARCH("PD Lubes",E117))),"Pre-Delivery","") | E117: Reliability Spares - 10,8K CEU SWS - GVT- Eltronic | F117: GVT Electronics | H117: Spares | L117: PCTC | M117: 2431 | N117: EUR | O117: Eltronic FuelTech A/S | P117: Checking
A118: Glovis LightHouse | C118: GLIG-60088/26-1 | D118: =IF(OR(ISNUMBER(SEARCH("Pre Delivery",E118)),ISNUMBER(SEARCH("Pre-Delivery",E118)),ISNUMBER(SEARCH("Predelivery",E118)),ISNUMBER(SEARCH("PD -",E118)),ISNUMBER(SEARCH("PD Lubes",E118))),"Pre-Delivery","") | E118: Gas meters | F118: Gas Meters | H118: Spares | L118: PCTC | M118: 2400 | N118: EUR | O118: POSEIDON MARINE SUPPLIES LTD | P118: Checking
...

Sheet Insights
B2: Goal: To identify suppliers for potential bulk discounts opportunities 1. Breakdown: Vessel Category > Category > Line items > Suppliers 2. Identify common items with key suppliers across vessel categories 3. Consolidate spend items with suppliers and highlight potential areas to seek further discounts
B10: Contract Status | C10: (Multiple Items)
B12: PO Values | C12: Projects
B13: Row Labels | C13: Glovis Lander | D13: Glovis LightHouse | E13: Glovis Link | F13: Glovis Logos | G13: Glovis Loyal | H13: Glovis Luminous | I13: (blank) | J13: Grand Total
B14: Spares | C14: 0 | D14: 1057357 | E14: 0 | F14: 0 | G14: 0 | H14: 0 | J14: 1057357
B15: Air driven HP Pump - For hydraulic nuts for M/E | D15: 0 | J15: 0
B16: #N/A | D16: 0 | J16: 0
B17: Alcometer | E17: 0 | J17: 0
B18: #N/A | E18: 0 | J18: 0
B19: Bosch GLM-50 or Laser Distance Measuring Tool | E19: 0 | J19: 0
B20: #N/A | E20: 0 | J20: 0
B21: Buyer Supply - 10,800 PCTC Citadel VHF/GPS and UHF ANTENNA system | D21: 39000 | J21: 39000
B22: West Nautical Pte Ltd | D22: 39000 | J22: 39000
B23: Citadel VHF/GPS and UHF ANTENNA system | C23: 0 | D23: 0 | J23: 0
B24: #N/A | C24: 0 | J24: 0
B25: #N/A | D25: 0 | J25: 0
B26: DF Tools | E26: 0 | J26: 0
B27: #N/A | E27: 0 | J27: 0
B28: Domestic refrigerators 200 litres for rec rooms to be added to stores supplies | E28: 0 | J28: 0
B29: #N/A | E29: 0 | J29: 0
B30: EV Lance | E30: 0 | J30: 0
B31: #N/A | E31: 0 | J31: 0
B32: FLIR ESPro and E6 Pro | G32: 0 | J32: 0
B33: #N/A | G33: 0 | J33: 0
B34: FS-ITBP -luminous | H34: 0 | J34: 0
B35: #N/A | H35: 0 | J35: 0
B36: FS-ITBP Additional Item | G36: 0 | H36: 0 | J36: 0
B37: #N/A | G37: 0 | H37: 0 | J37: 0
B38: FS-ITBP CABLES | G38: 0 | H38: 0 | J38: 0
B39: #N/A | G39: 0 | H39: 0 | J39: 0
B40: FS-ITBP MISC LAB KIT | G40: 0 | H40: 0 | J40: 0
B41: #N/A | G41: 0 | H41: 0 | J41: 0
B42: FS-KVH-GSI | H42: 0 | J42: 0
B43: #N/A | H43: 0 | J43: 0
B44: FS-LENOVO-Luminous | H44: 0 | J44: 0
B45: #N/A | H45: 0 | J45: 0
B46: FS-VLINK CABLE | G46: 0 | J46: 0
B47: #N/A | G47: 0 | J47: 0
B48: FS-X10-SILVERPEAK | H48: 0 | J48: 0
B49: #N/A | H49: 0 | J49: 0
B50: Garbage Compactor | D50: 4350 | J50: 4350
B51: Vessel Link Marine Supply & Service Ltd | D51: 4350 | J51: 4350
B52: Gas Cylinders | D52: 0 | J52: 0
B53: #N/A | D53: 0 | J53: 0
B54: Gas meters | E54: 0 | J54: 0
B55: #N/A | E55: 0 | J55: 0
B56: Glycol | E56: 0 | J56: 0
B57: #N/A | E57: 0 | J57: 0
B58: Jonghap - PCTC Loose Fittings Procurement | D58: 486174 | J58: 486174
B59: Jonghap Maritime Engineering Inc. | D59: 486174 | J59: 486174
B60: Main Engine - Additional Spares | D60: 0 | J60: 0
B61: #N/A | D61: 0 | J61: 0
B62: Manual chain blocks | E62: 0 | J62: 0
B63: #N/A | E63: 0 | J63: 0
B64: Mooring Rope | D64: 80788 | J64: 80788
B65: XINGLUN ROPE CABLE CO.,LTD | D65: 80788 | J65: 80788
B66: Ozone sterliser | E66: 0 | J66: 0
B67: #N/A | E67: 0 | J67: 0
B68: PD - RSC Envirologic | C68: 0 | E68: 0 | F68: 0 | G68: 0 | H68: 0 | J68: 0
B69: #N/A | C69: 0 | E69: 0 | F69: 0 | G69: 0 | H69: 0 | J69: 0
B70: Pre Delivery - Cryogenic PPE | G70: 0 | H70: 0 | J70: 0
B71: #N/A | G71: 0 | H71: 0 | J71: 0
B72: Pre Delivery - FLIR Camera | H72: 0 | J72: 0
B73: #N/A | H73: 0 | J73: 0
B74: Pre Delivery - Garbage Compactor | C74: 0 | F74: 0 | G74: 0 | H74: 0 | J74: 0
B75: #N/A | C75: 0 | F75: 0 | G75: 0 | H75: 0 | J75: 0
B76: Pre Delivery - LNG Bunkering Equipment | C76: 0 | H76: 0 | J76: 0
B77: #N/A | C77: 0 | H77: 0 | J77: 0
B78: Pre Delivery - Sample Cooler | C78: 0 | D78: 10858 | E78: 0 | F78: 0 | G78: 0 | H78: 0 | J78: 10858
B79: #N/A | C79: 0 | E79: 0 | F79: 0 | G79: 0 | H79: 0 | J79: 0
B80: Drew Marine USA, Inc | D80: 10858 | J80: 10858
B81: Pre Delivery - Seatab | C81: 0 | H81: 0 | J81: 0
B82: #N/A | C82: 0 | H82: 0 | J82: 0
B83: Publications | E83: 0 | J83: 0
B84: #N/A | E84: 0 | J84: 0
B85: Receptacles | D85: 0 | E85: 0 | J85: 0
B86: #N/A | E86: 0 | J86: 0
B87: #N/A | D87: 0 | J87: 0
B88: Reefer cable and plugs extensions | D88: 0 | E88: 0 | J88: 0
B89: #N/A | E89: 0 | J89: 0
B90: #N/A | D90: 0 | J90: 0
B91: Reliability - Donghwa Spares for BOG Compressor | D91: 7060 | E91: 0 | F91: 0 | G91: 0 | J91: 7060
B92: #N/A | E92: 0 | F92: 0 | G92: 0 | J92: 0
B93: DONGHWA ENTEC CO. ,LTD | D93: 7060 | J93: 7060
B94: Reliability HP Pump Skid | D94: 0 | J94: 0
B95: #N/A | D95: 0 | J95: 0
B96: Reliability Nitrogen Generator | D96: 12020 | J96: 12020
B97: Air Products AS | D97: 12020 | J97: 12020
B98: Reliability RO-RO Equipment (Main & Centre Ramp spares + inner Ramp spares) | D98: 0 | J98: 0
B99: #N/A | D99: 0 | J99: 0
B100: Reliability Spares - 10,8K CEU SWS - GVT- Eltronic | E100: 0 | F100: 0 | G100: 0 | J100: 0
B101: #N/A | E101: 0 | F101: 0 | G101: 0 | J101: 0
B102: Reliability Spares - Fire detection system | C102: 0 | D102: 9933 | E102: 0 | F102: 0 | G102: 0 | H102: 0 | J102: 9933
B103: #N/A | C103: 0 | E103: 0 | F103: 0 | G103: 0 | H103: 0 | J103: 0
B104: Consilium Marine and Safety Canada | D104: 9933 | J104: 9933
B105: Reliability Spares - PCTC-Seaspan - Boilers QUOT26012103 | C105: 0 | D105: 23968 | E105: 0 | F105: 0 | G105: 0 | H105: 0 | J105: 23968
B106: #N/A | C106: 0 | E106: 0 | F106: 0 | G106: 0 | H106: 0 | J106: 0
B107: Kangrim Industries Company Limited | D107: 23968 | J107: 23968
B108: Reliabiltiy Spares - Gas Detection System | C108: 0 | D108: 28136 | E108: 0 | F108: 0 | G108: 0 | H108: 0 | J108: 28136
B109: #N/A | C109: 0 | E109: 0 | F109: 0 | G109: 0 | H109: 0 | J109: 0
...

Sheet 📊 Fleet Summary
A1: 🚢 Newbuild PO Summary
A2: Vessel names and shipyards pull automatically from each vessel sheet. All counts update live.
A4: Vessel Name | B4: Shipyard | C4: Not Created | D4: To Be Created | E4: Pending Approval | F4: Approved & Issued | G4: Pending Delivery | H4: Delivered | I4: Total POs | J4: % Issued | K4: % Delivered
A5: ='Glovis Lighthouse'!C2 -> Glovis Lighthouse | B5: ='Glovis Lighthouse'!C3 -> SWS - Shanghai Waigaoqiao Shipbuilding Co., Ltd. | C5: =COUNTIF('Glovis Lighthouse'!E35:E140,"Not Created") -> 25 | D5: =COUNTIF('Glovis Lighthouse'!E35:E73,"To Be Created") -> 0 | E5: =COUNTIF('Glovis Lighthouse'!E35:E73,"Pending Approval") -> 0 | F5: =COUNTIF('Glovis Lighthouse'!E35:E73,"Approved & Issued") -> 0 | G5: =COUNTIF('Glovis Lighthouse'!E35:E73,"Pending Delivery") -> 23 | H5: =COUNTIF('Glovis Lighthouse'!E35:E73,"Delivered") -> 3 | I5: =COUNTA('Glovis Lighthouse'!B35:B73) -> 39 | J5: =IF(I5>0,(F5+G5)/I5,0) -> 0.58974359 | K5: =IF(I5>0,H5/I5,0) -> 0.076923077
A6: ='Glovis Link'!C2 -> Glovis Link | B6: ='Glovis Link'!C3 -> SWS | C6: =COUNTIF('Glovis Link'!E11:E151,"Not Created") -> 1 | D6: =COUNTIF('Glovis Link'!E11:E113,"To Be Created") -> 0 | E6: =COUNTIF('Glovis Link'!E11:E113,"Pending Approval") -> 9 | F6: =COUNTIF('Glovis Link'!E11:E113,"Approved & Issued") -> 0 | G6: =COUNTIF('Glovis Link'!E11:E113,"Pending Delivery") -> 23 | H6: =COUNTIF('Glovis Link'!E11:E113,"Delivered") -> 0 | I6: =COUNTA('Glovis Link'!B11:B113) -> 39 | J6: =IF(I6>0,(F6+G6)/I6,0) -> 0.58974359 | K6: =IF(I6>0,H6/I6,0) -> 0
A7: ='Glovis Logos'!C2 -> Glovis Logos | B7: ='Glovis Logos'!C3 -> SWS | C7: =COUNTIF('Glovis Logos'!E11:E151,"Not Created") -> 0 | D7: =COUNTIF('Glovis Logos'!E11:E113,"To Be Created") -> 0 | E7: =COUNTIF('Glovis Logos'!E11:E113,"Pending Approval") -> 6 | F7: =COUNTIF('Glovis Logos'!E11:E113,"Approved & Issued") -> 0 | G7: =COUNTIF('Glovis Logos'!E11:E113,"Pending Delivery") -> 19 | H7: =COUNTIF('Glovis Logos'!E11:E113,"Delivered") -> 0 | I7: =COUNTA('Glovis Logos'!B11:B113) -> 31 | J7: =IF(I7>0,(F7+G7)/I7,0) -> 0.61290323 | K7: =IF(I7>0,H7/I7,0) -> 0
A8: ='Glovis Loyal'!C2 -> Glovis Loyal | B8: ='Glovis Loyal'!C3 -> SWS | C8: =COUNTIF('Glovis Loyal'!E11:E151,"Not Created") -> 0 | D8: =COUNTIF('Glovis Loyal'!E11:E111,"To Be Created") -> 0 | E8: =COUNTIF('Glovis Loyal'!E11:E111,"Pending Approval") -> 5 | F8: =COUNTIF('Glovis Loyal'!E11:E111,"Approved & Issued") -> 0 | G8: =COUNTIF('Glovis Loyal'!E11:E111,"Pending Delivery") -> 6 | H8: =COUNTIF('Glovis Loyal'!E11:E111,"Delivered") -> 0 | I8: =COUNTA('Glovis Loyal'!B11:B111) -> 29 | J8: =IF(I8>0,(F8+G8)/I8,0) -> 0.20689655 | K8: =IF(I8>0,H8/I8,0) -> 0
A9: ='Glovis Lander'!C2 -> Glovis Lander | B9: ='Glovis Lander'!C3 -> GSI: Guangzhou United International Shipping Agency Co., Ltd | C9: =COUNTIF('Glovis Lander'!F11:F150,"Not Created") -> 1 | D9: =COUNTIF('Glovis Lander'!F11:F110,"To Be Created") -> 0 | E9: =COUNTIF('Glovis Lander'!F11:F110,"Pending Approval") -> 4 | F9: =COUNTIF('Glovis Lander'!F11:F110,"Approved & Issued") -> 0 | G9: =COUNTIF('Glovis Lander'!F11:F110,"Pending Delivery") -> 30 | H9: =COUNTIF('Glovis Lander'!F11:F110,"Delivered") -> 6 | I9: =COUNTA('Glovis Lander'!B11:B110) -> 56 | J9: =IF(I9>0,(F9+G9)/I9,0) -> 0.53571429 | K9: =IF(I9>0,H9/I9,0) -> 0.10714286
A10: ='Glovis Luminous'!C2 -> 0 | B10: ='Glovis Luminous'!C3 -> 0 | C10: =COUNTIF('Glovis Luminous'!E11:E150,"Not Created") -> 0 | D10: =COUNTIF('Glovis Luminous'!E11:E110,"To Be Created") -> 0 | E10: =COUNTIF('Glovis Luminous'!E11:E110,"Pending Approval") -> 5 | F10: =COUNTIF('Glovis Luminous'!E11:E110,"Approved & Issued") -> 0 | G10: =COUNTIF('Glovis Luminous'!E11:E110,"Pending Delivery") -> 11 | H10: =COUNTIF('Glovis Luminous'!E11:E110,"Delivered") -> 0 | I10: =COUNTA('Glovis Luminous'!B11:B110) -> 28 | J10: =IF(I10>0,(F10+G10)/I10,0) -> 0.39285714 | K10: =IF(I10>0,H10/I10,0) -> 0
A11: ='Vessel 7'!C2 -> 0 | B11: ='Vessel 7'!C3 -> 0 | C11: =COUNTIF('Vessel 7'!E11:E150,"Not Created") -> 0 | D11: =COUNTIF('Vessel 7'!E11:E110,"To Be Created") -> 0 | E11: =COUNTIF('Vessel 7'!E11:E110,"Pending Approval") -> 0 | F11: =COUNTIF('Vessel 7'!E11:E110,"Approved & Issued") -> 0 | G11: =COUNTIF('Vessel 7'!E11:E110,"Pending Delivery") -> 0 | H11: =COUNTIF('Vessel 7'!E11:E110,"Delivered") -> 0 | I11: =COUNTA('Vessel 7'!B11:B110) -> 0 | J11: =IF(I11>0,(F11+G11)/I11,0) -> 0 | K11: =IF(I11>0,H11/I11,0) -> 0
A12: ='Vessel 8'!C2 -> 0 | B12: ='Vessel 8'!C3 -> 0 | C12: =COUNTIF('Vessel 8'!E11:E150,"Not Created") -> 0 | D12: =COUNTIF('Vessel 8'!E11:E110,"To Be Created") -> 0 | E12: =COUNTIF('Vessel 8'!E11:E110,"Pending Approval") -> 0 | F12: =COUNTIF('Vessel 8'!E11:E110,"Approved & Issued") -> 0 | G12: =COUNTIF('Vessel 8'!E11:E110,"Pending Delivery") -> 0 | H12: =COUNTIF('Vessel 8'!E11:E110,"Delivered") -> 0 | I12: =COUNTA('Vessel 8'!B11:B110) -> 0 | J12: =IF(I12>0,(F12+G12)/I12,0) -> 0 | K12: =IF(I12>0,H12/I12,0) -> 0
A13: FLEET TOTAL | C13: =SUM(C5:C12) -> 27 | D13: =SUM(D5:D12) -> 0 | E13: =SUM(E5:E12) -> 29 | F13: =SUM(F5:F12) -> 0 | G13: =SUM(G5:G12) -> 112 | H13: =SUM(H5:H12) -> 9 | I13: =SUM(I5:I12) -> 222 | J13: =IF(I13>0,(F13+G13)/I13,0) -> 0.5045045 | K13: =IF(I13>0,H13/I13,0) -> 0.040540541

Sheet Glovis Lander
A1: 🚢 Vessel Purchase Order Tracker
A2: Vessel Name: | C2: Glovis Lander | G2: ← e.g. Seaspan New York
A3: Shipyard: | C3: GSI: Guangzhou United International Shipping Agency Co., Ltd | G3: ← e.g. YZJ Shipyard
A4: Vessel Delivery Date: | C4: 46212 | E4: ← Enter date as: 01-Jun-2025
E5: PO Number | F5: PO Name | G5: Category | H5: Status | I5: PO Issue Date | J5: Req. Delivery Date | K5: Reason / Remarks | L5: Responsible | M5: Supplier Name | N5: Po Currency | O5: Po Value | P5: Contract Status
A6: Not Created | B6: To Be Created | C6: Pending Approval | E6: Approved & Issued | F6: Pending Delivery | G6: Delivered | I6: Total POs | J6: % Issued | K6: % Delivered
A7: =COUNTIF(F11:F110,"Not Created") -> 1 | B7: =COUNTIF(F11:F110,"To Be Created") -> 0 | C7: =COUNTIF(F11:F110,"Pending Approval") -> 4 | E7: =COUNTIF(F11:F110,"Approved & Issued") -> 0 | F7: =COUNTIF(F11:F110,"Pending Delivery") -> 30 | G7: =COUNTIF(F11:F110,"Delivered") -> 6 | I7: =COUNTA(B11:B110) -> 56 | J7: =IF(I7>0,(E7+F7)/I7,0) -> 0.53571429 | K7: =IF(I7>0,G7/I7,0) -> 0.10714286
A9: 📅 Date fields: Enter dates as DD-MMM-YYYY format (e.g. 15-Jan-2025). Columns F & G are date columns.
A10: S/N | B10: PO Number | C10: PO Name | E10: Category | F10: Status | G10: PO Issue Date | I10: Req. Delivery Date | J10: Reason / Remarks
A11: 1 | B11: GLAN-60031/26-1 | C11: Reliabiltiy Spares - Gas Detection System | E11: Spares | F11: Pending Delivery | G11: 06-03-2026 | J11: To advise Shipping Address
A12: 2 | B12: GLAN-60024/26-1 | C12: FS-ITBP MISC LAB KIT | E12: Others | F12: Pending Delivery | G12: 24-02-2026 | J12: IT Po
A13: 3 | B13: GLAN-60004/26-1 | C13: FS-VLINK-2411005 | E13: Others | F13: Pending Delivery | G13: 19-01-2026 | J13: IT Po
A14: 4 | B14: GLAN-60022/26-1 | C14: Shipyard Extra Buyer Supply - Hinas SVM SEASPAN 10.8K PCTC | E14: Spares | F14: Pending Delivery | G14: 17-02-2026 | J14: Status Awaited from Hinas
A15: 5 | B15: GLAN-60017/26-1 | C15: Pre Delivery - Garbage Compactor | E15: Spares | F15: Delivered | G15: 06-02-2026 | J15: As per POD from V-Link
A16: 6 | B16: GLAN-60007/26-1 | C16: FS-X10-LANDER | E16: Others | F16: Pending Delivery | G16: 21-01-2026 | J16: IT Po
A17: 7 | B17: GLAN-60002/26-1 | C17: Interface PO -24110005 | E17: Others | F17: Pending Delivery | G17: 14-01-2026 | J17: IT Po
A18: 8 | B18: GLAN-60012/26-1 | C18: Predelivery - Additional Grades | E18: Lube Oil | F18: Pending Delivery | G18: 23-01-2026 | J18: As per Delivery date Total Delivery date is pending
A19: 9 | B19: GLAN-60026/26-1 | C19: Predelivery Lubes - Order # 2 (5713853485) | E19: Lube Oil | F19: Delivered | G19: 02-03-2026 | J19: As per Email
A20: 10 | B20: GLAN-60032/26-1 | C20: Reliability Spares - Fire detection system | E20: Spares | F20: Pending Delivery | G20: 06-03-2026 | J20: To advise Shipping Address
A21: 11 | B21: GLAN-60023/26-1 | C21: FS-ITBP Additional Item | E21: Others | F21: Pending Delivery | G21: 19-02-2026 | J21: IT Po
A22: 12 | B22: GLAN-60033/26-1 | C22: Pre Delivery - LNG Bunkering Equipment | E22: Spares | F22: Pending Delivery | G22: 46100 | J22: Po Issued on Trelleborg
A23: 13 | B23: GLAN-60001/26-1 | C23: Shipyard Extra Owner supply - Captains Eye | E23: Spares | F23: Pending Delivery | G23: 15-01-2026 | J23: Awaiting status from Captain Eye
A24: 14 | B24: GLAN-60010/26-1 | C24: FS-SIHUI-lander | E24: Others | F24: Pending Delivery | G24: 26-01-2026 | J24: IT Po
A25: 15 | B25: GLAN-60025/26-1 | C25: Pre Delivery - Lubes Order# 3 (5715069528) | E25: Lube Oil | F25: Delivered | G25: 02-03-2026 | J25: As per Delivery Date on the Quotes
A26: 16 | B26: GLAN-60019/26-1 | C26: Pre Delivery - Spray Pipes | E26: Spares | F26: Delivered | G26: 06-02-2026 | J26: As per POD from V-Link
A27: 17 | B27: GLAN-60003/26-1 | C27: Pre Delivery - Additional Grade Copco Roto-XtendDuty | E27: Lube Oil | F27: Delivered | G27: 15-01-2026 | J27: As per POD from V-Link
A28: 18 | B28: GLAN-60011/26-1 | C28: Pre Delivery - Spray Pipes | E28: Lube Oil | F28: Delivered | G28: 01-02-2026 | J28: As per POD from V-Link
A29: 19 | B29: GLAN-60020/26-1 | C29: FS-LENOVO-Lander | E29: Others | F29: Pending Delivery | G29: 10-02-2026 | J29: IT Po
A30: 20 | B30: GLAN-60006/26-1 | C30: FS-ITBP -lander | E30: Others | F30: Pending Delivery | G30: 21-01-2026 | J30: IT Po
A31: 21 | B31: GLAN-60034/26-1 | C31: Pre Delivery - QCDC | E31: Spares | F31: Pending Delivery | G31: 06-03-2026 | J31: Po Issued on Trelleborg
A32: 22 | B32: GLAN-60015/26-1 | C32: FS-KVH-LANDER UPDATED | E32: Others | F32: Pending Delivery | G32: 23-01-2026 | J32: IT Po
A33: 23 | B33: GLAN-60030/26-1 | C33: PD - RSC Envirologic | E33: Spares | F33: Pending Delivery | J33: Qty to be Approved by Seyi'
A34: 24 | B34: GLAN-60005/26-1 | C34: FS-VLINK-Accessories | E34: Others | F34: Pending Delivery | G34: 21-01-2026 | J34: IT Po
A35: 25 | B35: GLAN-60008/26 | C35: FS -AST-LANDER | E35: Others | F35: Pending Delivery | G35: 20-01-2026 | J35: IT Po
A36: 26 | B36: GLAN-60009/26-1 | C36: FS -AST-LANDER | E36: Others | F36: Pending Delivery | G36: 21-01-2026 | J36: IT Po
A37: 27 | B37: GLAN-60016/26-1 | C37: FS-Interface-Lander | E37: Others | F37: Pending Delivery | G37: 29-01-2026 | J37: IT Po
A38: 28 | B38: GLAN-60028/26 | C38: Reliability Spares - PCTC-Seaspan - Boilers QUOT26012103 | E38: Spares | F38: Pending Approval | G38: 25-02-2026 | J38: Po to be Approved
A39: 29 | B39: GLAN-60018/26-1 | C39: SHIPYARD EXTRA OWNER SUPPLY- Abanaki Skimmers | E39: Spares | F39: Pending Delivery | G39: 12-02-2026 | J39: Frederic to advise the Po status
A40: 30 | B40: GLAN-60001/25-2 | C40: Lubricants - Pre Delivery | E40: Lube Oil | F40: Pending Delivery | G40: 25-11-2025 | J40: As per the Delivery date of OC
A41: 31 | B41: GLAN-60021/26-1 | C41: FS-ITBP CABLES | E41: Others | F41: Pending Delivery | G41: 10-02-2026 | J41: IT Po
A42: 32 | C42: Reliability Spares - 10,8K CEU SWS - GVT- Korval | J42: Awaiting offer from Korval
A43: 33 | C43: Citadel VHF/GPS and UHF ANTENNA system | J43: Po 000030180276 Dummy Po raised as Vendor not enlisted in Jibe
A44: 34 | C44: Reliability Spares - PCTC-Seaspan - Boilers QUOT26012103 | J44: Awaiting offer from Kangrim
A45: 35 | C45: PCTC Loose Fittings Procurement | J45: Vendor to be enlisted
A46: 36 | C46: Shipyard Extra (Owner supply) - 10800 CEU LNG PCTC _x0013_ Consilium SMiG Integration | J46: Asked to cancel
A47: 37 | B47: GLAN-60041/26 | C47: Impa Stores Stationery
A48: 38 | B48: GLAN-60042/26 | C48: Impa Stores - SOPEP
A49: 39 | B49: GLAN-60043/26 | C49: Impa Stores - Deck
A50: 40 | B50: GLAN-60044/26 | C50: Impa Stores - Bridge
A51: 41 | B51: GLAN-60045/26 | C51: Impa Stores - Gym
A52: 42 | B52: GLAN-60046/26 | C52: Impa Stores - Crew
A53: 43 | B53: GLAN-60047/26 | C53: Impa Stores - FFE
A54: 44 | B54: GLAN-60048/26 | C54: Impa Stores - Company Stationery
A55: 45 | C55: Impa Stores - BA Compressor
A56: 46 | B56: GLAN-60049/26 | C56: Impa Stores - ACC
A57: 47 | B57: GLAN-60050/26 | C57: Impa Stores - Galley
A58: 48 | B58: GLAN-60052/26 | C58: Impa Stores - Engine
A59: 49 | B59: GLAN-60051/26 | C59: Impa Stores - Engine
A60: 50 | B60: GLAN-60053/26 | C60: Impa Stores - Engine
A61: 51 | B61: GLAN-60054/26 | C61: Impa Stores - Engine
A62: 52 | B62: GLAN-60055/26 | C62: Impa Stores - Electric
A63: 53 | C63: Impa Stores - Instrumenation
A64: 54 | B64: GLAN-60060/26-1 | C64: Ultrasonic Cleaning system - 230V | E64: Stores | F64: Pending Delivery | J64: Shall be Delivered at Yard as advised
A65: 55 | B65: GLAN-60061/26-1 | C65: OPA 90 KIT - 12-barrel kit | E65: Stores | F65: Pending Delivery | J65: Shall be Delivered at Yard as advised
A66: 56 | B66: GLAN-60062/26-1 | C66: H.P machine - 2pcs (prefer Branded - Karcher/ KEW) | E66: Stores | F66: Pending Delivery | J66: Shall be Delivered at Yard as advised
A67: 57 | C67: 2. LOTO Stickers
A68: 58 | B68: GLAN-60064/26 | C68: 3. Steam Splash Suit | E68: Stores | F68: Pending Approval | J68: Po to be Approved
A69: 59 | C69: 4. Chemical tags
A70: 60 | C70: 5. Trelleborg Safe lanes
A71: 61 | B71: GLAN-60037/26-1 | C71: Pre Delivery - Seatab | E71: Spares | F71: Pending Delivery | G71: 46098
A72: 62 | B72: GLAN-60039/26-1 | C72: FLIR ESPro and E6 Pro | E72: Stores | F72: Pending Delivery | J72: PO Issued on V-Link
A73: 63 | C73: 8. Explosion Proof Camera
A74: 64 | B74: GLAN-60035/26-1 | C74: Pre Delivery - Cryogenic PPE | E74: Stores | F74: Not Created | G74: 46098 | J74: To be Approved
A75: 65 | C75: 10. Temperature & Pressure Calibrators
A76: 66 | C76: 11. VISWA Line Samplers
A77: 67 | C77: 12. Standard Chinese stationery
A78: 68 | C78: 13. Air driven HP Pump - For hydraulic nuts for M/E - From Dan Marine or VLINK
A79: 69 | C79: Chemical
A80: 70 | B80: GLAN-60036/26-1 | C80: Mooring Rope | E80: Stores | F80: Pending Delivery | J80: Po issued on Xinglun
A81: 71 | C81: UHF Radio
A82: 72 | C82: Soot
A83: 73 | C83: Garbage Refrigerator
A84: 74 | B84: GLAN-60069/26 | C84: DF Tools | E84: Stores | F84: Pending Approval | J84: To be Approved
A85: 75 | C85: UHF Antenna
A86: 76 | B86: GLAN-60038/26-1 | C86: Pre Delivery - Sample Cooler | E86: Spares | F86: Pending Approval | G86: 46101 | J86: Qty 2 Pcs
A87: 77 | C87: Citadel Items
A88: 78 | C88: Stanchions
A89: 79
A90: 80
A91: 81
A92: 82
A93: 83
A94: 84
A95: 85
A96: 86
A97: 87
A98: 88
A99: 89
A100: 90
... A110: 100
...

Sheet Glovis Luminous
A1: 🚢 Vessel Purchase Order Tracker
A2: Vessel Name: | F2: ← e.g. Seaspan New York
A3: Shipyard: | F3: ← e.g. YZJ Shipyard
A4: Vessel Delivery Date: | D4: ← Enter date as: 01-Jun-2025
A6: Not Created | B6: To Be Created | C6: Pending Approval | D6: Approved & Issued | E6: Pending Delivery | F6: Delivered | G6: Total POs | H6: % Issued | I6: % Delivered
A7: =COUNTIF(E11:E110,"Not Created") -> 0 | B7: =COUNTIF(E11:E110,"To Be Created") -> 0 | C7: =COUNTIF(E11:E110,"Pending Approval") -> 5 | D7: =COUNTIF(E11:E110,"Approved & Issued") -> 0 | E7: =COUNTIF(E11:E110,"Pending Delivery") -> 11 | F7: =COUNTIF(E11:E110,"Delivered") -> 0 | G7: =COUNTA(B11:B110) -> 28 | H7: =IF(G7>0,(D7+E7)/G7,0) -> 0.39285714 | I7: =IF(G7>0,F7/G7,0) -> 0
A9: 📅 Date fields: Enter dates as DD-MMM-YYYY format (e.g. 15-Jan-2025). Columns F & G are date columns.
A10: S/N | B10: PO Number | C10: PO Name | D10: Category | E10: Status | F10: PO Issue Date | G10: Req. Delivery Date | H10: Reason / Remarks
A11: 1 | B11: GLUM-60015/26-1 | C11: PD - RSC Envirologic | E11: PO Created
A12: 2 | B12: GLUM-60003/26-1 | C12: FS-ITBP -luminous | E12: Pending Delivery | F12: 46055
A13: 3 | B13: GLUM-MVSP-60002/26-1 | C13: FS-X10-SILVERPEAK | E13: Pending Supplier Confirmation | F13: 46101
A14: 4 | B14: GLUM-60024/26-1 | C14: Service: LNG OPERATION MANUAL Development | E14: PO Created
A15: 5 | B15: GLUM-60006/26-1 | C15: Shipyard Extra Buyers Supply - Tripods and Spray Pipes | E15: Pending Delivery | F15: 46091
A16: 6 | B16: GLUM-60019/26-1 | C16: Shipyard Extra (buyer Supply) - QCDC -GSI | E16: Pending Supplier Confirmation | F16: 46101
A17: 7 | B17: GLUM-60016/26-1 | C17: Reliabiltiy Spares - Gas Detection System | E17: Pending Delivery | F17: 46087
A18: 8 | B18: GLUM-60008/26-1 | C18: Shipyard Extra Buyers Supply - Hinas SVM SEASPAN 10.8K PCTC | E18: Pending Supplier Confirmation | F18: 46070
A19: 9 | B19: GLUM-60010/26-1 | C19: FS-ITBP Additional Item | E19: Pending Delivery | F19: 46072
A20: 10 | B20: GLUM-60023/26-1 | C20: Pre Delivery - FLIR Camera | E20: Pending Delivery | F20: 46099
A21: 11 | B21: GLUM-60001/26-1 | C21: Shipyard Extra Owner supply - Captains Eye | E21: Pending Delivery | F21: 46037
A22: 12 | B22: GLUM-60017/26-1 | C22: Reliability Spares - Fire detection system | E22: Pending Delivery | F22: 46087
A23: 13 | B23: GLUM-60002/26-1 | C23: FS-KVH-GSI | E23: Pending Delivery | F23: 46048
A24: 14 | B24: GLUM-60022/26-1 | C24: Pre Delivery - Sample Cooler | E24: Pending Supplier Confirmation | F24: 46101
A25: 15 | B25: GLUM-60009/26-1 | C25: FS-ITBP CABLES | E25: Pending Supplier Confirmation | F25: 46071
A26: 16 | B26: GLUM-60007/26-1 | C26: FS-LENOVO-Luminous | E26: Pending Delivery | F26: 46066
... A32: 22 | B32: GLUM-60005/26-1 | C32: SHIPYARD EXTRA ONWER SUPPLY - Abanaki Skimmers | E32: Pending Supplier Confirmation | F32: 46065
A33: 23 | B33: GLUM-60014/26 | C33: Reliability Spares - PCTC-Seaspan - Boilers QUOT26012103 | E33: Pending Approval | F33: 46078 | H33: To be Approved
A34: 24 | B34: GLUM-60025/26 | C34: Ultrasonic Cleaner | D34: Stores | E34: Pending Approval | H34: To be Approved
A35: 25 | B35: GLUM-60026/26 | C35: OPA 90 KIT - 12-barrel kit | D35: Stores | E35: Pending Approval | H35: To be Approved
A36: 26 | B36: GLUM-60027/26 | C36: H.P machine - 2pcs (prefer Branded - Karcher/ KEW) | D36: Stores | E36: Pending Approval | H36: To be Approved
A37: 27 | B37: GLUM-60028/26 | C37: Steam Splash Suit | D37: Stores | E37: Pending Approval | H37: To be Approved
A38: 28 | B38: GLUM-60033/26 | C38: Gas Meter
A39: 29
A40: 30
A41: 31
A42: 32
A43: 33
A44: 34
A45: 35
A46: 36
A47: 37
A48: 38
A49: 39
A50: 40
... A110: 100

Sheet Glovis Lighthouse
A1: 🚢 Vessel Purchase Order Tracker
A2: Vessel Name: | C2: Glovis Lighthouse | F2: ← e.g. Seaspan New York
A3: Shipyard: | C3: SWS - Shanghai Waigaoqiao Shipbuilding Co., Ltd. | F3: ← e.g. YZJ Shipyard
A4: Vessel Delivery Date: | C4: 46179 | D4: ← Enter date as: 01-Jun-2025
A6: Not Created | B6: To Be Created | C6: Pending Approval | D6: Approved & Issued | E6: Pending Delivery | F6: Delivered | G6: Total POs | H6: % Issued | I6: % Delivered
A7: 2 | B7: 0 | C7: 7 | D7: 0 | E7: 28 | F7: 3 | G7: 39 | H7: 0.71794872 | I7: 0.076923077
A9: 📅 Date fields: Enter dates as DD-MMM-YYYY format (e.g. 15-Jan-2025). Columns F & G are date columns.
A10: S/N | B10: PO Number | C10: PO Name | D10: Category | E10: Status | F10: PO Issue Date | G10: Req. Delivery Date | H10: Reason / Remarks | I10: Responsible | J10: Supplier Name | K10: Po Currency | L10: Po Value | M10: Contract Status | S10: Contracted
C11: Oily Water Separator | D11: Alfa Laval | H11: Alfa Laval | I11: Quote reqd for Marpol Spared | J11: #N/A | K11: #N/A | L11: #N/A | M11: Contracted | S11: Not Contracted
C12: BWTS Spares | D12: Alfa Laval | H12: Alfa Laval | I12: Quote reqd for Marpol Spared | J12: #N/A | K12: #N/A | L12: #N/A | S12: Invalidated
A13: 82 | B13: GLIG-60077/26-1 | C13: Crew Care | D13: Chemicals | E13: Pending Delivery | H13: Drew Delivery at Yard | J13: Drew Marine USA, Inc | K13: USD | L13: 3075.32 | S13: Under Review
A14: 81 | B14: GLIG-60075/26-1 | C14: Pre Delivery - Engineering Products & Kits (DREW) | D14: Chemicals | E14: Pending Delivery | H14: Drew Delivery at Yard | J14: Drew Marine USA, Inc | K14: USD | L14: 20708.78
A15: 79 | B15: GLIG-60071/26-1 | C15: Refrigerant Equipment | D15: Chemicals | E15: Pending Delivery | H15: Drew Delivery at Yard | J15: Drew Marine USA, Inc | K15: USD | L15: 7739.92
A16: 78 | B16: GLIG-60078/26-1 | C16: Pre Delivery - Welding Equipment | D16: Chemicals | E16: Pending Delivery | H16: Drew Delivery at Yard | J16: Drew Marine USA, Inc | K16: USD | L16: 30943.48
A17: 76 | B17: GLIG-60070/26-1 | C17: Gases | D17: Chemicals | E17: Pending Delivery | H17: Drew Delivery at Yard | J17: Drew Marine USA, Inc | K17: USD | L17: 5327.36
A18: 74 | B18: GLIG-60068/26-1 | C18: Pre Delivery - Treatment Chemical | D18: Chemicals | E18: Pending Delivery | H18: Drew Delivery at Yard | J18: Drew Marine USA, Inc | K18: USD | L18: 9265.52
A19: 75 | B19: GLIG-60045/26-1 | C19: Maintenance Chemicals | D19: Chemicals | E19: Pending Delivery | H19: Drew Delivery at Yard | J19: Drew Marine USA, Inc | K19: USD | L19: 5339.14
C20: Sewage Traetment Plant | D20: CSSC Nanjing | H20: CSSC Nanjing | I20: Quote reqd for Marpol Spared | J20: #N/A | K20: #N/A | L20: #N/A
C21: Sewage Discharge P/P | D21: CSSC Nanjing | H21: CSSC Nanjing | I21: Quote reqd for Marpol Spared | J21: #N/A | K21: #N/A | L21: #N/A
A22: 23 | B22: GLIG-60030/26-1 | C22: Pre Delivery Lubes Order# 3 (5714478288) | D22: Lube Oil | E22: Delivered | F22: 46083 | H22: Delivered | J22: TotalEnergies Lubrifiants | K22: USD | L22: 305941.12
A23: 14 | B23: GLIG-60002/25-1 | C23: Pre-Delivery - Lubes | D23: Lube Oil | E23: Delivered | F23: 45958 | G23: 46017 | H23: Order #5713665401 shud be delivered | J23: TotalEnergies Lubrifiants | K23: USD | L23: 83442.94
A24: 27 | B24: GLIG-60001/25-1 | C24: Lubricants - Pre Delivery | D24: Lube Oil | E24: Pending Delivery | F24: 45951 | H24: OC #5713475236 | J24: TotalEnergies Lubrifiants | K24: USD | L24: 51229.5
B25: GLIG-60096/26-1 | C25: Final Sailing Qty of Lubes | D25: Lube Oil | E25: Pending Delivery | H25: Po Issued on Total 2 Pcs Kits | J25: TotalEnergies Lubrifiants | K25: USD | L25: 30700
A26: 33 | B26: GLIG-60025/26-1 | C26: PD Lubes - VLSQ61941 - Kaeser Fluid Rotary S-46X | D26: Lube Oil | E26: Delivered | F26: 46083 | H26: Delivered | J26: Vessel Link Marine Supply & Service Ltd | K26: USD | L26: 4413.5
A27: 99 | C27: RSC Lube oil - qty / Total for Glovis Lighthouse | D27: Lube Oil | E27: Not Created | H27: Total Lube Oil for BT for Glovis Lighthouse | I27: Sahaya to create Po for BT Oil on Total Qty 1 Drum | J27: #N/A | K27: #N/A | L27: #N/A
A28: 36 | B28: GLIG-60008/26-1 | C28: AST PO | D28: Others | E28: Pending Delivery | F28: 46037 | H28: IT PO | J28: Applied Satellite Technology Systems US LLC (AST Americas) | K28: USD | L28: 5765.71
A29: 20 | B29: GLIG-60021/26-1 | C29: FS-Interface-Light house | D29: Others | E29: Pending Delivery | F29: 46051 | G29: 46081 | H29: IT PO | J29: Interface Computer System Co. Ltd. | K29: HKD | L29: 260190.71
A30: 32 | B30: GLIG-60003/26-1 | C30: Interface PO | D30: Others | E30: Pending Delivery | F30: 46030 | G30: 46081 | H30: IT PO | J30: Interface Computer System Co. Ltd. | K30: HKD | L30: 55710
B31: GLIG-MVSP-60003/26-1 | C31: FS-Interface MTA adapter | D31: Others | J31: Interface Computer System Co. Ltd. | K31: HKD | L31: 1911
A32: 5 | B32: GLIG-60023/26-1 | C32: FS-ITBP CABLES | D32: Others | E32: Pending Delivery | F32: 46063 | G32: 46081 | H32: IT PO | J32: IT Blueprint Solutions Consulting Inc | K32: USD | L32: 1101.24
A33: 3 | B33: GLIG-60022/26-1 | C33: FS-LENOVO-Lighthouse | D33: Others | E33: Pending Delivery | F33: 46063 | G33: 46081 | H33: IT PO | J33: IT Blueprint Solutions Consulting Inc | K33: CAD | L33: 49418.82
A34: 21 | B34: GLIG-60012/26-1 | C34: FS-ITBP -glovis lighthouse | D34: Others | E34: Pending Delivery | F34: 46041 | G34: 46081 | H34: IT PO | J34: IT Blueprint Solutions Consulting Inc | K34: USD | L34: 29715.77
A35: 22 | B35: GLIG-60029/26-1 | C35: FS-ITBP MISC LAB KIT | D35: Others | E35: Pending Delivery | F35: 46077 | G35: 46081 | H35: IT PO | J35: IT Blueprint Solutions Consulting Inc | K35: USD | L35: 200.91
A36: 38 | B36: GLIG-60028/26-1 | C36: FS-ITBP Additional Item | D36: Others | E36: Pending Delivery | F36: 46072 | G36: 46081 | H36: IT PO | J36: IT Blueprint Solutions Consulting Inc | K36: USD | L36: 1494.12
A37: 17 | B37: GLIG-60019/26-1 | C37: FS-KVH -LIGHTHOUSE UPDATED | D37: Others | E37: Pending Delivery | F37: 46045 | H37: IT PO | J37: KVH Industries Inc | K37: USD | L37: 6775
B38: GLIG-60097/26-1 | D38: Others | E38: Pending Delivery | H38: IT PO | J38: KVH Industries Inc | K38: USD | L38: 4040
A39: 11 | B39: GLIG-60017/26-1 | C39: FS-SIHUI | D39: Others | E39: Pending Delivery | F39: 46048 | G39: 46081 | H39: IT PO | J39: SIHUI MARINE CO LTD | K39: USD | L39: 20000
A40: 10 | B40: GLIG-60013/26-1 | C40: FS-VLINK-Accessories | D40: Others | E40: Pending Delivery | F40: 46043 | H40: IT PO | J40: Vessel Link Marine Supply & Service Ltd | K40: USD | L40: 168
A41: 2 | B41: GLIG-60010/26-1 | C41: FS-VLINK-H1610 | D41: Others | E41: Pending Delivery | F41: 46041 | G41: 46081 | H41: IT PO | J41: Vessel Link Marine Supply & Service Ltd | K41: USD | L41: 25285
A42: 30 | B42: GLIG-60027/26-1 | C42: FS-VLINK CABLE | D42: Others | E42: Pending Delivery | F42: 46064 | G42: 46081 | H42: IT PO | J42: Vessel Link Marine Supply & Service Ltd | K42: USD | L42: 63
B43: GLIG-60067/26-1 | C43: Service: LNG OPERATION MANUAL Development | D43: Others | J43: VMT Co., Ltd | K43: USD | L43: 21500
A44: 12 | B44: GLIG-60036/26-1 | C44: Wartsila Training PCTC | D44: Others | E44: Not Created | F44: 46105 | H44: Service | J44: Wartsila Canada Inc. | K44: EUR | L44: 11760
A45: 8 | B45: GLIG-60015/26-1 | C45: FS-X10 | D45: Others | E45: Pending Delivery | F45: 46043 | G45: 46081 | H45: IT PO | J45: X10 Networks Inc. | K45: CAD | L45: 4281.08
A46: 15 | B46: GLIG-60020/26 | C46: Interface -equipment-lighthouse | D46: Others | E46: Not Created | F46: 46050 | H46: IT PO | J46: #N/A | K46: #N/A | L46: #N/A
A47: 9 | B47: GLIG-60018/26 | C47: FS-KVH-LIGHTHOUSE | D47: Others | E47: Not Created | F47: 46045 | H47: IT PO | J47: #N/A | K47: #N/A | L47: #N/A
A48: 29 | B48: GLIG-60016/26 | C48: Sihui Marine-light house | D48: Others | E48: Not Created | F48: 46042 | H48: IT PO | J48: #N/A | K48: #N/A | L48: #N/A
A49: 31 | B49: GLIG-60014/26 | C49: FS-X10 | D49: Others | E49: Not Created | F49: 46042 | G49: 46081 | H49: IT PO | J49: #N/A | K49: #N/A | L49: #N/A
A50: 7 | B50: GLIG-60009/26 | C50: FS-ITBP -1 | D50: Others | E50: Not Created | F50: 46038 | H50: IT PO | J50: #N/A | K50: #N/A | L50: #N/A
A51: 1 | B51: GLIG-60007/25 | C51: FS services | D51: Others | E51: Not Created | F51: 46014 | H51: IT PO | J51: #N/A | K51: #N/A | L51: #N/A
A52: 39 | B52: GLIG-60040/26-1 | C52: FS-VLINK-Starlink Accessories | D52: Others | E52: Pending Delivery | F52: 46086 | H52: IT PO | J52: #N/A | K52: #N/A | L52: #N/A
A53: 35 | B53: GLIG-60002/26 | C53: fs interface | D53: Others | E53: Not Created | F53: 46029 | H53: IT PO | J53: #N/A | K53: #N/A | L53: #N/A
A54: 28 | B54: GLIG-60032/26 | C54: FS-ITBP-LICENSES | D54: Others | E54: Not Created | F54: 46078 | H54: IT PO | J54: #N/A | K54: #N/A | L54: #N/A
A55: 34 | B55: GLIG-60001/26 | C55: FS | D55: Others | E55: Not Created | F55: 46028 | H55: IT PO | J55: #N/A | K55: #N/A | L55: #N/A
B56: GLIG-60081/26 | C56: FS-ITBP tax invoice | D56: Others | J56: #N/A | K56: #N/A | L56: #N/A
B57: GLIG-60082/26 | C57: fs-x10 sample test | D57: Others | J57: #N/A | K57: #N/A | L57: #N/A
A58: 97 | B58: GLIG-60098/26-1 | C58: Reliability Nitrogen Generator | D58: Spares | E58: Pending Delivery | H58: Po issued | J58: Air Products AS | K58: USD | L58: 12019.56
A59: 26 | B59: GLIG-60024/26-1 | C59: Shipyard Extra Buyer Supply - HiNAS SVM 10800 A-Q-2025-09-02_R0 | D59: Spares | E59: Delivered | F59: 46070 | H59: Delivered | J59: Avikus Co., Ltd. | K59: USD | L59: 63600.15
A60: 25 | B60: GLIG-60005/26-1 | C60: Shipyard Extra Owner supply - Captains Eye | D60: Spares | E60: Pending Delivery | F60: 46037 | H60: Shipped at Yard | I60: Seyi to confirm on the Installation cost if Any | J60: Captain's Eye | K60: USD | L60: 224200
A61: 24 | B61: GLIG-60038/26-1 | C61: Reliability Spares - Fire detection system | D61: Spares | E61: Pending Delivery | F61: 46087 | H61: Shipped to RMS | J61: Consilium Marine and Safety Canada | K61: USD | L61: 9933
A62: 16 | B62: GLIG-60037/26-1 | C62: Reliabiltiy Spares - Gas Detection System | D62: Spares | E62: Pending Delivery | F62: 46083 | H62: Shipped to RMS | J62: Consilium Marine and Safety Canada | K62: USD | L62: 28136
A63: 37 | B63: GLIG-60005/25-1 | C63: SHIPYARD EXTRA OWNER SUPPLY - SWS-10.8k CEU extra cost for SMiG application | D63: Spares | E63: Pending Delivery | F63: 46065 | H63: Checking with supplier if this is commissioed | J63: Consilium Marine and Safety Canada | K63: USD | L63: 19300
A64: 96 | B64: GLIG-60048/26-1 | C64: Reliability - Donghwa Spares for BOG Compressor | D64: Spares | E64: Pending Delivery | F64: 46111 | H64: Awaiting Readiness | J64: DONGHWA ENTEC CO. ,LTD | K64: USD | L64: 7060
A65: 89 | B65: GLIG-60047/26-1 | C65: Pre Delivery - Sample Cooler | D65: Spares | E65: Delivered | F65: 46101 | H65: Delivered | J65: Drew Marine USA, Inc | K65: USD | L65: 10858
A66: 4 | B66: GLIG-60026/26-2 | C66: Reliability Spares - 10,8K CEU SWS - GVT- Eltronic | D66: Spares | E66: Pending Delivery | F66: 46084 | H66: Po ready asked for Shipping Details | J66: Eltronic FuelTech A/S | K66: EUR | L66: 2431
A67: 40 | B67: GLIG-60042/26-1 | C67: SHIPYARD EXTRA OWNER SUPPLY- Abanaki Skimmers | D67: Spares | E67: Delivered | F67: 46100 | H67: Order shipped to Yard Fedex #889699529619 | I67: Delivered | J67: Hermont Marine Inc | K67: USD | L67: 10325
A68: 18 | B68: GLIG-60034/26-1 | C68: Jonghap - PCTC Loose Fittings Procurement | D68: Spares | E68: Pending Delivery | F68: 46084 | H68: Weekly updated Provided | I68: GLIG-60034/26-1 cancelled and GLIG-60034/26-2 to be approved | J68: Jonghap Maritime Engineering Inc. | K68: USD | L68: 486174.37
A69: 13 | B69: GLIG-60033/26-1 | C69: Reliability Spares - PCTC-Seaspan - Boilers QUOT26012103 | D69: Spares | E69: Pending Delivery | F69: 46087 | H69: Awaiting Readiness | J69: Kangrim Industries Company Limited | K69: USD | L69: 23967.9
A70: 92 | B70: GLIG-60079/26-1 | C70: Main Engine Spares | D70: Spares | E70: Pending Delivery | H70: Awaiting Readiness | J70: MAN B and W Diesel-Copenhagen Denmark | K70: EUR | L70: 215083.08
A71: 119 | B71: GLIG-60094/26-1 | C71: EV Lance | D71: Spares | E71: Pending Delivery | H71: Awaiting Readiness | J71: MOL Techno Trade Ltd | K71: JPY | L71: 1794590
A72: 66 | B72: GLIG-60046/26-1 | C72: Seatab | D72: Spares | E72: Pending Delivery | H72: Awaiting Readiness | I72: Cannot deliver at China, will be deliverde at Sailing Port | J72: OneOcean AS | K72: USD | L72: 3887.28
A73: 110 | B73: GLIG-60088/26-1 | C73: Gas meters | D73: Spares | E73: Pending Delivery | H73: Poseidon working on a earlier date | J73: POSEIDON MARINE SUPPLIES LTD | K73: EUR | L73: 2400.16
A74: 41 | B74: GLIG-60043/26-1 | C74: Garbage Compactor | D74: Spares | E74: Delivered | H74: Delivered as per POD | J74: Vessel Link Marine Supply & Service Ltd | K74: USD | L74: 4350
A75: 84 | B75: GLIG-60100/26-1 | C75: UHF Radio (Handheld) | D75: Spares | E75: Pending Delivery | H75: Po issued for 6 Vsl's | J75: Vessel Link Marine Supply & Service Ltd | K75: USD | L75: 32128
B76: GLIG-60093/26-1 | C76: VISWA Line Samplers | D76: Spares | E76: Pending Delivery | H76: Awaiting Readiness | J76: Viswam Limited | K76: USD | L76: 1630
A77: 93 | B77: GLIG-60080/26-1 | C77: Aux. Engine Spares | D77: Spares | E77: Pending Delivery | H77: Po issued on Wartsila | J77: Wartsila Canada Inc. | K77: EUR | L77: 113839.26
A78: 19 | B78: GLIG-60087/26-1 | C78: Buyer Supply - 10,800 PCTC Citadel VHF/GPS and UHF ANTENNA system | D78: Spares | E78: Pending Delivery | F78: 46083 | H78: Po issued on West Nautical | J78: West Nautical Pte Ltd | K78: USD | L78: 39000.01
A79: 83 | B79: GLIG-60066/26-1 | C79: Mooring Rope | D79: Spares | E79: Pending Delivery | H79: Po issued on Xinglun | J79: XINGLUN ROPE CABLE CO.,LTD | K79: USD | L79: 80788.25
A80: 6 | B80: GLIG-60003/25 | C80: Citadel VHF/GPS and UHF ANTENNA system | D80: Spares | E80: Delivered | H80: PO 000030180276 Dummy Po raised as Vendor not enlisted in Jibe | I80: Sahaya to create Po in Jibe | J80: #N/A | K80: #N/A | L80: #N/A
A81: 73 | B81: GLIG-60085/26-1 | C81: Air driven HP Pump - For hydraulic nuts for M/E | D81: Spares | E81: Pending Delivery | H81: Po issued on 6 Vsl's | J81: #N/A | K81: #N/A | L81: #N/A
A82: 94 | C82: Reliability RO-RO Equipment (Main & Centre Ramp spares + inner Ramp spares) | D82: Spares | E82: Not Created | H82: Quotes recd by OPS | I82: Kshitij to fwd to enlist in Database | J82: #N/A | K82: #N/A | L82: #N/A
A83: 95 | C83: Reliability HP Pump Skid | D83: Spares | E83: Not Created | H83: Supplier not seen in Jibe | J83: #N/A | K83: #N/A | L83: #N/A
A84: 107 | C84: Reefer cable and plugs extensions | D84: Spares | E84: Not Created | H84: Seyi to confirmif this is needed | I84: Monirul to discuss with Seyi | J84: #N/A | K84: #N/A | L84: #N/A
A85: 110 | B85: GLIG-60115/26 | C85: Gas Cylinders | D85: Spares | E85: Pending Approval | H85: Poseidon working on a earlier date | J85: #N/A | K85: #N/A | L85: #N/A
A86: 116 | C86: Thermal Stop PO | D86: Spares | E86: Not Created | H86: Onhold as advised by Abhishek | I86: Abhishek to review and advise further | J86: #N/A | K86: #N/A | L86: #N/A
A87: 120 | C87: Receptacles | D87: Spares | E87: Not Created | H87: Already Delivered at Yard 220 VAC 1PH, Buyer Supplied Equipment | I87: Monirul to confirm with Seyi/ Su | J87: #N/A | K87: #N/A | L87: #N/A
A88: 65 | C88: Trelleborg Safe lanes | D88: Spares | E88: Not Created | H88: Delivered by Yard on Sws Vsl's | J88: #N/A | K88: #N/A | L88: #N/A
B89: GLIG-60101/26 | C89: Main Engine - Additional Spares | D89: Spares | E89: Pending Approval | I89: Monirul to Approve Po | J89: #N/A | K89: #N/A | L89: #N/A
A90: 50 | B90: GLIG-60103/26-1 | C90: IMPA Stores - BA Compressor | D90: Stores | E90: Pending Delivery | H90: Dan Marine at Yard | J90: Dan Marine Group Ltd. | K90: USD | L90: 6929.02
A91: 70 | B91: GLIG-60102/26-1 | C91: Temperature Calibrators | D91: Stores | E91: Pending Delivery | H91: Po raised for 6 Vsl's | J91: Dan Marine Group Ltd. | K91: USD | L91: 5860
B92: GLIG-60102/26-1 | C92: Pressure Calibrators | D92: Stores | E92: Pending Delivery | H92: Po raised for 6 Vsl's | J92: Dan Marine Group Ltd. | K92: USD | L92: 5860
A93: 56 | B93: GLIG-60063/26-1 | C93: IMPA Stores - Engine | D93: Stores | E93: Pending Delivery | H93: Po issued on Fuji Marine | J93: Fuji Marine Logistics Shunyang(Shanghai) Co., LIMITED | K93: USD | L93: 6223.59
A94: 52 | B94: GLIG-60059/26-1 | C94: IMPA Stores - Galley | D94: Stores | E94: Pending Delivery | H94: Po issued on Fuji Marine | J94: Fuji Marine Logistics Shunyang(Shanghai) Co., LIMITED | K94: USD | L94: 1518.33
A95: 53 | B95: GLIG-60060/26-1 | C95: IMPA Stores - Engine | D95: Stores | E95: Pending Delivery | H95: Po issued on Fuji Marine | J95: Fuji Marine Logistics Shunyang(Shanghai) Co., LIMITED | K95: USD | L95: 6363.01
A96: 51 | B96: GLIG-60058/26-1 | C96: IMPA Stores - ACC | D96: Stores | E96: Pending Delivery | H96: Po issued on Fuji Marine | J96: Fuji Marine Logistics Shunyang(Shanghai) Co., LIMITED | K96: USD | L96: 4987.42
A97: 45 | B97: GLIG-60053/26-1 | C97: IMPA Stores - Bridge | D97: Stores | E97: Pending Delivery | H97: Po issued on Fuji Marine | J97: Fuji Marine Logistics Shunyang(Shanghai) Co., LIMITED | K97: USD | L97: 1145.26
A98: 49 | B98: GLIG-60057/26-1 | C98: IMPA Stores - Company Stationery | D98: Stores | E98: Pending Delivery | H98: Po issued on Longwind | J98: HONGKONG LONGWIND MARINE SERVICE CO LIMITED | K98: USD | L98: 385.72
A99: 64 | B99: GLIG-60091/26-1 | C99: Chemical tags | D99: Stores | E99: Pending Delivery | H99: Po raised on 6 Vsl's | I99: Shipped to RMS | J99: HONGKONG LONGWIND MARINE SERVICE CO LIMITED | K99: USD | L99: 1889.1
A100: 62 | B100: GLIG-60106/26-1 | C100: LOTO Stickers | D100: Stores | E100: Pending Delivery | H100: Po raised on 6 Vsl's | I100: Awaiting Readiness | J100: Loto Master Inc | K100: USD | L100: 386.2
A101: 42 | B101: GLIG-60050/26-1 | C101: IMPA Stores Stationery | D101: Stores | E101: Pending Delivery | H101: Po issued on Fuji Marine | J101: RMS Marine Service Company Ltd. | K101: USD | L101: 2697.63
A102: 109 | B102: GLIG-60104/26-1 | C102: Glycol | D102: Stores | E102: Pending Delivery | H102: Po raised on 6 Vsl's | J102: RMS Marine Service Company Ltd. | K102: USD | L102: 2260
...

Sheet Glovis Link
A1: 🚢 Vessel Purchase Order Tracker
A2: Vessel Name: | C2: Glovis Link | F2: ← e.g. Seaspan New York
A3: Shipyard: | C3: SWS | F3: ← e.g. YZJ Shipyard
A4: Vessel Delivery Date: | D4: ← Enter date as: 01-Jun-2025
A6: Not Created | B6: To Be Created | C6: Pending Approval | D6: Approved & Issued | E6: Pending Delivery | F6: Delivered | G6: Total POs | H6: % Issued | I6: % Delivered
A7: =COUNTIF(E11:E113,"Not Created") -> 1 | B7: =COUNTIF(E11:E113,"To Be Created") -> 0 | C7: =COUNTIF(E11:E113,"Pending Approval") -> 9 | D7: =COUNTIF(E11:E113,"Approved & Issued") -> 0 | E7: =COUNTIF(E11:E113,"Pending Delivery") -> 23 | F7: =COUNTIF(E11:E113,"Delivered") -> 0 | G7: =COUNTA(B11:B113) -> 39 | H7: =IF(G7>0,(D7+E7)/G7,0) -> 0.58974359 | I7: =IF(G7>0,F7/G7,0) -> 0
A9: 📅 Date fields: Enter dates as DD-MMM-YYYY format (e.g. 15-Jan-2025). Columns F & G are date columns.
A10: S/N | B10: PO Number | C10: PO Name | D10: Category | E10: Status | F10: PO Issue Date | G10: Req. Delivery Date | H10: Reason / Remarks
A11: 1 | B11: GLIN-60016/26-1 | C11: FS-VLINK CABLE | D11: Others | E11: Pending Delivery | F11: 11-02-2026 | G11: 46079 | H11: IT Po
A12: 2 | B12: GLIN-60019/26 | C12: Reliability Spares - PCTC-Seaspan - Boilers QUOT26012103_R00 | D12: Spares | E12: Pending Approval | F12: 25-02-2026 | H12: Po to be Approved
A13: 3 | B13: GLIN-60005/26-1 | C13: FS-ITBP -glovis link | D13: Others | E13: Pending Delivery | F13: 19-01-2026 | G13: 46079 | H13: IT Po
A14: 4 | B14: GLIN-60013/26-1 | C14: FS-ITBP CABLES | D14: Others | E14: Pending Delivery | F14: 10-02-2026 | G14: 46079 | H14: IT Po
A15: 5 | B15: GLIN-60009/26-1 | C15: FS-SIHUI-link | D15: Others | E15: Pending Delivery | F15: 26-01-2026 | G15: 46079 | H15: IT Po
A16: 6 | B16: GLIN-60012/26-1 | C16: FS-LENOVO-Link | D16: Others | E16: Pending Delivery | F16: 10-02-2026 | G16: 46079 | H16: IT Po
A17: 7 | B17: GLIN-60011/26-1 | C17: Shipyard Extra (Owner supply) - 10800 CEU LNG PCTC _x0013_ Consilium SMiG Integration | D17: Spares | E17: Pending Delivery | F17: 12-02-2026 | H17: It’s a Service, they shall advise the delivery dates shortly
A18: 8 | B18: GLIN-60004/26-1 | C18: FS-VLINK-H1612 | D18: Others | E18: Pending Delivery | F18: 19-01-2026 | G18: 46079 | H18: IT Po
A19: 9 | B19: GLIN-60017/26-1 | C19: FS-ITBP Additional Item | D19: Others | E19: Pending Delivery | F19: 19-02-2026 | G19: 46079 | H19: IT Po
A20: 10 | B20: GLIN-60020/26 | C20: Reliability Spares - PCTC-Seaspan - Boilers QUOT26012103 | E20: Not Created | F20: 25-02-2026 | H20: Duplicate
A21: 11 | B21: GLIN-60006/26-1 | C21: FS-VLINK-Accessories | D21: Others | E21: Pending Delivery | F21: 21-01-2026 | G21: 46079 | H21: IT Po
A22: 12 | B22: GLIN-60003/26-1 | C22: Interface PO-H1612 | D22: Others | E22: Pending Delivery | F22: 19-01-2026 | G22: 46079 | H22: IT Po
A23: 13 | B23: GLIN-60023/26-1 | C23: Reliabiltiy Spares - Gas Detection System | D23: Spares | E23: Pending Delivery | F23: 06-03-2026 | H23: To advise Shipping Address
A24: 14 | B24: GLIN-60007/26-1 | C24: FS-X10 | D24: Others | E24: Pending Delivery | F24: 46043 | G24: 46079 | H24: IT Po
A25: 15 | B25: GLIN-60015/26-1 | C25: Shipyard Extra Buyers supply - Hinas SVM SEASPAN 10.8K PCTC | D25: Spares | E25: Pending Delivery | F25: 17-02-2026 | H25: Seyi to advsie Email Id's of Avikus
A26: 16 | B26: GLIN-60010/26-1 | C26: FS-KVH-SWS | D26: Others | E26: Pending Delivery | F26: 26-01-2026 | G26: 46079 | H26: IT Po
A27: 17 | B27: GLIN-60008/26-1 | C27: FS -AST-LINK | D27: Others | E27: Pending Delivery | F27: 21-01-2026 | G27: 46079 | H27: IT Po
A28: 18 | B28: GLIN-60002/26-1 | C28: Predelivery - Visga 46 5715010143 | D28: Lube Oil | E28: Pending Delivery | F28: 19-02-2026 | G28: 46127 | H28: Awaiting Delivery
A29: 19 | B29: GLIN-60024/26-1 | C29: Reliability Spares - Fire detection system | D29: Spares | E29: Pending Delivery | F29: 06-03-2026 | H29: To advise Shipping Address
A30: 20 | B30: GLIN-60021/26 | C30: FS-ITBP-LICENSES | D30: Others | E30: Pending Delivery | F30: 25-02-2026 | G30: 46079 | H30: IT Po
A31: 21 | B31: GLIN-60025/26-1 | C31: FS-VLINK-Starlink Accessories | D31: Others | E31: Pending Delivery | F31: 46086 | G31: 46079 | H31: IT Po
A32: 22 | B32: GLIN-60026/26-1 | C32: SHIPYARD EXTRA OWNER SUPPLY- Abanaki Skimmers | D32: Spares | E32: Pending Approval | F32: 46091 | H32: Po shared with supplier, to be approved
A33: 23 | B33: GLIN-60018/26-1 | C33: FS-ITBP MISC LAB KIT | D33: Others | E33: Pending Delivery | F33: 24-02-2026 | G33: 46079 | H33: IT Po
A34: 24 | B34: GLIN-60022/26-1 | C34: PD - RSC Envirologic | D34: Spares | E34: Pending Delivery | H34: Seyi to advise exact Qty
A35: 25 | B35: GLIN-60014/26-2 | C35: Reliability Spares - 10,8K CEU SWS - GVT- Eltronic | D35: Spares | E35: Pending Approval | F35: 46112 | H35: Po to be Approved
A36: 26 | B36: GLIN-60033/26-1 | C36: LNG OPERATION MANUAL Development
A37: 27 | C37: Citadel VHF/GPS and UHF ANTENNA system | H37: Po 000030180277 Dummy Po raised as Vendor not enlisted in Jibe
A38: 28 | C38: PCTC Loose Fittings Procurement | H38: Vendor to be enlisted in database
A39: 29 | C39: Buyer Supply - 10,800 PCTC Citadel VHF/GPS and UHF ANTENNA system | H39: Dummy Po shared awaiting vendor to be enlisted
A40: 30 | B40: GLIN-60001/26 | C40: Shipyard Extra Owner supply - Captains Eye | H40: To check with BG as unable to see this Po
A41: 31 | B41: GLIN-60026/26-1 | C41: SHIPYARD EXTRA OWNER SUPPLY- Abanaki Skimmers | D41: Spares | E41: Pending Supplier Confirmation | F41: 46091 | H41: Po to be created however shared with Hermont
A42: 32 | B42: GLIN-60027/26-1 | C42: Pre Delivery - Garbage Compactor | E42: Pending Delivery | F42: 46094 | H42: Po to be Approved by VM
A43: 33 | C43: Impa Stores Stationery
A44: 34 | C44: Impa Stores - SOPEP
A45: 35 | C45: Impa Stores - Deck
A46: 36 | C46: Impa Stores - Bridge
A47: 37 | C47: Impa Stores - Gym
A48: 38 | C48: Impa Stores - Crew
A49: 39 | C49: Impa Stores - FFE
A50: 40 | C50: Impa Stores - Company Stationery
A51: 41 | C51: Impa Stores - BA Compressor
A52: 42 | C52: Impa Stores - ACC
A53: 43 | C53: Impa Stores - Galley
A54: 44 | C54: Impa Stores - Engine
... A59: 49 | C59: Impa Stores - Instrumenation
A60: 50 | B60: GLIN-60034/26 | C60: Ultrasonic Cleaning system - 230V | D60: Stores | E60: Pending Approval | H60: To be Approved
A61: 51 | B61: GLIN-60035/26 | C61: OPA 90 KIT - 12-barrel kit | D61: Stores | E61: Pending Approval | H61: To be Approved
A62: 52 | B62: GLIN-60036/26 | C62: H.P machine - 2pcs (prefer Branded - Karcher/ KEW)
A63: 53 | C63: 2. LOTO Stickers
A64: 54 | B64: GLIN-60037/26 | C64: 3. Steam Splash Suit | D64: Stores | E64: Pending Approval | H64: To be Approved
A65: 55 | C65: 4. Chemical tags
A66: 56 | C66: 5. Trelleborg Safe lanes | H66: Delivered by Yard on Sws Vsl's
A67: 57 | B67: GLIN-60029/26-1 | C67: Pre Delivery - Seatab | F67: 46098
A68: 58 | B68: GLIN-60032/26-1 | C68: FLIR ESPro and E6 Pro | D68: Stores | E68: Pending Delivery | H68: Po issued on V-Link
A69: 59 | C69: 8. Explosion Proof Camera
A70: 60 | B70: GLIN-60028/26-1 | C70: Pre Delivery - Cryogenic PPE | D70: Stores | E70: Pending Supplier Confirmation | F70: 46101 | H70: Po to be Approved
A71: 61 | C71: 10. Temperature & Pressure Calibrators
A72: 62 | C72: 11. VISWA Line Samplers
A73: 63 | C73: 12. Standard Chinese stationery
A74: 64 | C74: 13. Air driven HP Pump - For hydraulic nuts for M/E - From Dan Marine or VLINK
A75: 65 | C75: Chemical
A76: 66 | C76: Mooring Rope
A77: 67 | C77: UHF Radio
A78: 68 | C78: Soot
A79: 69 | C79: Garbage Refrigerator
A80: 70 | C80: DF Tools
A81: 71 | C81: UHF Antenna
A82: 72 | B82: GLIN-60030/26-1 | C82: Pre Delivery - Sample Cooler | D82: Spares | E82: Pending Approval | F82: 46101 | H82: Qty 2 Pcs
A83: 73 | C83: Citadel Items
A84: 74 | C84: Stanchions
A85: 75 | C85: Main Engine
A86: 76 | C86: Aux. Engine
A87: 77 | C87: RO-RO Equipment (Main & Centre Ramp spares + inner Ramp spares)
A88: 78 | C88: HP Pump Skid
A89: 79 | B89: GLIN-60031/26-1 | C89: Reliability - Donghwa Spares for BOG Compressor | D89: Spares | E89: Pending Approval | F89: 46111 | H89: Po to be Approved
A90: 80 | C90: Nitrogen Generator
A91: 81
A92: 82 | C92: RSC Lube oil - qty
A93: 83 | C93: QC DC
A94: 84 | C94: Manuals for all equipment- priority for BWTS, STP, OWS, EMGCY AC, EMCY GEN
A95: 85 | C95: Domestic refrigerators 200 litres for rec rooms to be added to stores supplies
A96: 86 | C96: Breathing air compressor
A97: 87 | C97: ozone sterliser
A98: 88 | C98: suez light
A99: 89 | C99: Item no 11, loose equipment for emergency operation of roro equipment
A100: 90 | C100: Reefer cable and plugs extensions
A101: 91 | C101: Manual chain blocks
A102: 92 | C102: Glycol
A103: 93 | B103: GLIN-60042/26 | C103: Gas meters | D103: Spares | E103: Pending Approval | H103: Po to be Approved
A104: 94 | C104: Welding machine in Workshop 440 v
A105: 95 | C105: Service Car and Forlift
A106: 96 | C106: DF Tools
...

Sheet Glovis Logos
A1: 🚢 Vessel Purchase Order Tracker
A2: Vessel Name: | C2: Glovis Logos | F2: ← e.g. Seaspan New York
A3: Shipyard: | C3: SWS | F3: ← e.g. YZJ Shipyard
A4: Vessel Delivery Date: | D4: ← Enter date as: 01-Jun-2025
A6: Not Created | B6: To Be Created | C6: Pending Approval | D6: Approved & Issued | E6: Pending Delivery | F6: Delivered | G6: Total POs | H6: % Issued | I6: % Delivered
A7: =COUNTIF(E11:E113,"Not Created") -> 0 | B7: =COUNTIF(E11:E113,"To Be Created") -> 0 | C7: =COUNTIF(E11:E113,"Pending Approval") -> 6 | D7: =COUNTIF(E11:E113,"Approved & Issued") -> 0 | E7: =COUNTIF(E11:E113,"Pending Delivery") -> 19 | F7: =COUNTIF(E11:E113,"Delivered") -> 0 | G7: =COUNTA(B11:B113) -> 31 | H7: =IF(G7>0,(D7+E7)/G7,0) -> 0.61290323 | I7: =IF(G7>0,F7/G7,0) -> 0
A9: 📅 Date fields: Enter dates as DD-MMM-YYYY format (e.g. 15-Jan-2025). Columns F & G are date columns.
A10: S/N | B10: PO Number | C10: PO Name | D10: Category | E10: Status | F10: PO Issue Date | G10: Req. Delivery Date | H10: Reason / Remarks
A11: 17 | B11: GLOG-60001/26-1 | C11: Shipyard Extra Owner supply - Captains Eye | D11: Spares | E11: Pending Delivery | F11: 15-01-2026 | H11: Awaiting Readiness
A12: 13 | B12: GLOG-60002/26-1 | C12: FS-KVH-SWS-LOGOS | D12: Others | E12: Pending Delivery | F12: 26-01-2026 | H12: IT Po
A13: 12 | B13: GLOG-60003/26 | C13: FS-AST-SAMPLE | D13: Others | E13: Pending Delivery | F13: 26-01-2026 | H13: IT Po
A14: 4 | B14: GLOG-60005/26-1 | C14: FS-AST-LOGOS | D14: Others | E14: Pending Delivery | F14: 27-01-2026 | G14: 46079 | H14: IT Po
A15: 11 | B15: GLOG-60006/26-1 | C15: FS-ITBP -LOGOS | D15: Others | E15: Pending Delivery | F15: 27-01-2026 | H15: IT Po
A16: 9 | B16: GLOG-60007/26-1 | C16: Shipyard Extra (owner supply) 10800 CEU LNG PCTC _x0013_ Consilium SMiG Integration | D16: Spares | E16: Pending Delivery | F16: 12-02-2026 | H16: Awaiting Readiness
A17: 3 | B17: GLOG-60008/26-1 | C17: FS-LENOVO-Logos | D17: Others | E17: Pending Delivery | F17: 11-02-2026 | G17: 46079 | H17: IT Po
A18: 8 | B18: GLOG-60009/26-1 | C18: Reliability Spares - 10,8K CEU SWS - GVT- Eltronic | D18: Spares | E18: Pending Delivery | F18: 03-03-2026 | H18: Awaiting Readiness
A19: 1 | B19: GLOG-60010/26-1 | C19: Shipyard Extra Buyers Supply - Hinas SVM SEASPAN 10.8K PCTC | D19: Spares | E19: Pending Delivery | F19: 17-02-2026 | H19: Seyi to advsie Email Id's of Avikus
A20: 5 | B20: GLOG-60011/26-1 | C20: FS-VLINK CABLE | D20: Others | E20: Pending Delivery | F20: 11-02-2026 | G20: 46079 | H20: IT Po
A21: 14 | B21: GLOG-60012/26-1 | C21: FS-ITBP CABLES | D21: Others | E21: Pending Delivery | F21: 18-02-2026 | H21: IT Po
A22: 15 | B22: GLOG-60013/26-1 | C22: FS-ITBP Additional Item | D22: Others | E22: Pending Delivery | F22: 19-02-2026 | H22: IT Po
A23: 10 | B23: GLOG-60014/26-1 | C23: FS-ITBP MISC LAB KIT | D23: Others | E23: Pending Delivery | F23: 24-02-2026 | H23: IT Po
A24: 18 | B24: GLOG-60016/26 | C24: Reliability Spares - PCTC-Seaspan - Boilers QUOT26012103 | D24: Spares | E24: Pending Approval | F24: 25-02-2026 | H24: Po to be Approved
A25: 6 | B25: GLOG-60017/26-1 | C25: PD - RSC Envirologic | D25: Spares | E25: Pending Delivery | H25: Seyi to advise Qty
A26: 16 | B26: GLOG-60018/26-1 | C26: Reliabiltiy Spares - Gas Detection System | D26: Spares | E26: Pending Delivery | F26: 06-03-2026 | H26: To advise Shipping Address
A27: 7 | B27: GLOG-60019/26-1 | C27: Reliability Spares - Fire detection system | D27: Spares | E27: Pending Delivery | F27: 06-03-2026 | H27: To advise Shipping Instructions
A28: 2 | B28: GLOG-60020/26-1 | C28: SHIPYARD EXTRA OWNER SUPPLY- Abanaki Skimmers | D28: Spares | E28: Pending Delivery | F28: 46091 | H28: Po shared with supplier, to be approved
B29: GLOG-60020/26-1 | C29: SHIPYARD EXTRA OWNER SUPPLY- Abanaki Skimmers | D29: Spares | E29: Pending Supplier Confirmation | F29: 46091 | H29: Po to be created however shared to Supplier
B30: GLOG-60021/26-1 | C30: Pre Delivery - Garbage Compactor | D30: Spares | E30: Pending Delivery | F30: 46094 | H30: Po to be Approved by VM
A31: 49 | B31: GLOG-60022/26-1 | C31: Pre Delivery - Cryogenic PPE | D31: Stores | E31: Pending Supplier Confirmation | F31: 46101 | H31: Po to be Approved
A32: 61 | B32: GLOG-60024/26-1 | C32: Pre Delivery - Sample Cooler | D32: Spares | E32: Pending Approval | F32: 46101 | H32: Qty 2 Pcs to be Approved
A33: 68 | B33: GLOG-60025/26-1 | C33: Reliability - Donghwa Spares for BOG Compressor | D33: Spares | E33: Pending Supplier Confirmation | F33: 46111 | H33: To be Approved
A34: 47 | B34: GLOG-60026/26-1 | C34: FLIR ESPro and E6 Pro | D34: Stores | E34: Pending Delivery | H34: Po Issued to V-Link
B35: GLOG-60027/26-1 | C35: Service: LNG OPERATION MANUAL Development
A36: 19 | C36: Citadel VHF/GPS and UHF ANTENNA system | H36: Po 000030180276 Dummy Po raised as Vendor not enlisted in Jibe
A37: 20 | C37: PCTC Loose Fittings Procurement | H37: Vendor to be enlisted in database
A38: 21 | C38: Buyer Supply - 10,800 PCTC Citadel VHF/GPS and UHF ANTENNA system | H38: Dummy Po 000030180276 created as Vendor not in Jibe
A39: 22 | C39: Impa Stores Stationery
A40: 23 | C40: Impa Stores - SOPEP
A41: 24 | C41: Impa Stores - Deck
A42: 25 | C42: Impa Stores - Bridge
A43: 26 | C43: Impa Stores - Gym
A44: 27 | C44: Impa Stores - Crew
A45: 28 | C45: Impa Stores - FFE
A46: 29 | C46: Impa Stores - Company Stationery
A47: 30 | C47: Impa Stores - BA Compressor
A48: 31 | C48: Impa Stores - ACC
A49: 32 | C49: Impa Stores - Galley
A50: 33 | C50: Impa Stores - Engine
... A55: 38 | C55: Impa Stores - Instrumenation
A56: 39 | B56: GLOG-60028/26 | C56: Ultrasonic Cleaning system - 230V | D56: Stores | E56: Pending Approval | H56: To be Approved
A57: 40 | B57: GLOG-60029/26 | C57: OPA 90 KIT - 12-barrel kit | D57: Stores | E57: Pending Approval | H57: To be Approved
A58: 41 | B58: GLOG-60030/26 | C58: H.P machine - 2pcs (prefer Branded - Karcher/ KEW) | D58: Stores | E58: Pending Approval | H58: To be Approved
A59: 42 | C59: 2. LOTO Stickers
A60: 43 | B60: GLOG-60031/26 | C60: 3. Steam Splash Suit | D60: Stores | E60: Pending Approval | H60: To be Approved
A61: 44 | C61: 4. Chemical tags
A62: 45 | C62: 5. Trelleborg Safe lanes | H62: Delivered by Yard on Sws Vsl's
A63: 46 | B63: GLOG-60023/26-1 | C63: Pre Delivery - Seatab | F63: 46098
A64: 48 | C64: 8. Explosion Proof Camera
A65: 50 | C65: 10. Temperature & Pressure Calibrators
A66: 51 | C66: 11. VISWA Line Samplers
A67: 52 | C67: 12. Standard Chinese stationery
A68: 53 | C68: 13. Air driven HP Pump - For hydraulic nuts for M/E - From Dan Marine or VLINK
A69: 54 | C69: Chemical
A70: 55 | C70: Mooring Rope
A71: 56 | C71: UHF Radio
A72: 57 | C72: Soot
A73: 58 | C73: Garbage Refrigerator
A74: 59 | C74: DF Tools
A75: 60 | C75: UHF Antenna
... A82: 69 | C82: Nitrogen Generator
A83: 70
A84: 71 | C84: RSC Lube oil - qty
A85: 72 | C85: QC DC
A86: 73 | C86: Manuals for all equipment- priority for BWTS, STP, OWS, EMGCY AC, EMCY GEN
A87: 74 | C87: Domestic refrigerators 200 litres for rec rooms to be added to stores supplies
A88: 75 | C88: Breathing air compressor
A89: 76 | C89: ozone sterliser
A90: 77 | C90: suez light
A91: 78 | C91: Item no 11, loose equipment for emergency operation of roro equipment
A92: 79 | C92: Reefer cable and plugs extensions
A93: 80 | C93: Manual chain blocks
A94: 81 | C94: Glycol
A95: 82 | B95: GLOG-60035/26 | C95: Gas meters
A96: 83 | C96: Welding machine in Workshop 440 v
A97: 84 | C97: Service Car and Forlift
A98: 85
A99: 86
A100: 87
A101: 88
A102: 89
A103: 90
A104: 91
A105: 92
A106: 93
A107: 94
A108: 95
A109: 96
... A113: 100

Sheet Glovis Loyal
A1: 🚢 Vessel Purchase Order Tracker
A2: Vessel Name: | C2: Glovis Loyal | F2: ← e.g. Seaspan New York
A3: Shipyard: | C3: SWS | F3: ← e.g. YZJ Shipyard
A4: Vessel Delivery Date: | D4: ← Enter date as: 01-Jun-2025
A6: Not Created | B6: To Be Created | C6: Pending Approval | D6: Approved & Issued | E6: Pending Delivery | F6: Delivered | G6: Total POs | H6: % Issued | I6: % Delivered
A7: =COUNTIF(E11:E111,"Not Created") -> 0 | B7: =COUNTIF(E11:E111,"To Be Created") -> 0 | C7: =COUNTIF(E11:E111,"Pending Approval") -> 5 | D7: =COUNTIF(E11:E111,"Approved & Issued") -> 0 | E7: =COUNTIF(E11:E111,"Pending Delivery") -> 6 | F7: =COUNTIF(E11:E111,"Delivered") -> 0 | G7: =COUNTA(B11:B111) -> 29 | H7: =IF(G7>0,(D7+E7)/G7,0) -> 0.20689655 | I7: =IF(G7>0,F7/G7,0) -> 0
A9: 📅 Date fields: Enter dates as DD-MMM-YYYY format (e.g. 15-Jan-2025). Columns F & G are date columns.
A10: S/N | B10: PO Number | C10: PO Name | D10: Category | E10: Status | F10: PO Issue Date | G10: Req. Delivery Date | H10: Reason / Remarks
A11: 6 | B11: GLOY-60001/26-1 | C11: Shipyard Extra Owner supply - Captains Eye | F11: 15-01-2026
A12: 2 | B12: GLOY-60002/26-1 | C12: FS-KVH-SWS-LOYAL | D12: Others | E12: Pending Delivery | F12: 26-01-2026 | H12: IT Po
A13: 7 | B13: GLOY-60004/26-1 | C13: FS-AST-LOYOL | F13: 27-01-2026
A14: 8 | B14: GLOY-60005/26-1 | C14: FS-ITBP -LOYAL | F14: 27-01-2026
A15: 9 | B15: GLOY-60006/26-1 | C15: SHIPYARD EXTRA OWNER SUPLPY - 10800 CEU LNG PCTC _x0013_ Consilium SMiG Integration | F15: 12-02-2026
A16: 13 | B16: GLOY-60007/26-1 | C16: FS-LENOVO-Loyal | F16: 13-02-2026
A17: 16 | B17: GLOY-60008/26-1 | C17: Reliability Spares - 10,8K CEU SWS - GVT- Eltronic | F17: 03-03-2026
A18: 5 | B18: GLOY-60009/26-1 | C18: Shipyard Extra Buyers Supply - Hinas SVM SEASPAN 10.8K PCTC | D18: Spares | E18: Pending Delivery | F18: 17-02-2026 | H18: Seyi to advsie Email Id's of Avikus
A19: 12 | B19: GLOY-60010/26-1 | C19: FS-VLINK CABLE | F19: 11-02-2026
A20: 14 | B20: GLOY-60012/26-1 | C20: FS-ITBP CABLES | F20: 18-02-2026
A21: 10 | B21: GLOY-60013/26-1 | C21: FS-ITBP Additional Item | F21: 19-02-2026
A22: 1 | B22: GLOY-60014/26-1 | C22: FS-ITBP MISC LAB KIT | D22: Others | E22: Pending Delivery | F22: 24-02-2026 | H22: IT Po
A23: 3 | B23: GLOY-60016/26 | C23: Reliability Spares - PCTC-Seaspan - Boilers QUOT26012103 | D23: Spares | E23: Pending Approval | F23: 25-02-2026 | H23: Po to be Approved
A24: 11 | B24: GLOY-60017/26-1 | C24: PD - RSC Envirologic
A25: 17 | B25: GLOY-60018/26-1 | C25: Reliabiltiy Spares - Gas Detection System | F25: 06-03-2026
A26: 4 | B26: GLOY-60019/26-1 | C26: Reliability Spares - Fire detection system | D26: Spares | E26: Pending Delivery | F26: 06-03-2026 | H26: To advise Shipping Instructions
A27: 15 | B27: GLOY-60020/26-1 | C27: SHIPYARD EXTRA OWNER SUPPLY- Abanaki Skimmers | D27: Spares | E27: Pending Supplier Confirmation | F27: 46091 | H27: Po to be created however shared to Supplier
A28: 18 | B28: GLOY-60021/26-1 | C28: Pre Delivery - Garbage Compactor | D28: Spares | E28: Pending Delivery | F28: 46094 | H28: To be approved by VM
A29: 46 | B29: GLOY-60022/26-1 | C29: Pre Delivery - Cryogenic PPE | D29: Stores | E29: Pending Supplier Confirmation | F29: 46101 | H29: Po to be Approved
A30: 58 | B30: GLOY-60024/26-1 | C30: Pre Delivery - Sample Cooler | D30: Spares | E30: Pending Supplier Confirmation | F30: 46101 | H30: Qty 2 Pcs
A31: 65 | B31: GLOY-60025/26-1 | C31: Reliability - Donghwa Spares for BOG Compressor | D31: Spares | E31: Pending Supplier Confirmation | F31: 46111 | H31: To be Approved
A32: 44 | B32: GLOY-60026/26-1 | C32: FLIR ESPro and E6 Pro | D32: Stores | E32: Pending Delivery | H32: Po issued on V-Link
B33: GLOY-60027/26-1 | C33: Service: LNG OPERATION MANUAL Development
A34: 19 | C34: Impa Stores Stationery
A35: 20 | C35: Impa Stores - SOPEP
A36: 21 | C36: Impa Stores - Deck
A37: 22 | C37: Impa Stores - Bridge
A38: 23 | C38: Impa Stores - Gym
A39: 24 | C39: Impa Stores - Crew
A40: 25 | C40: Impa Stores - FFE
A41: 26 | C41: Impa Stores - Company Stationery
A42: 27 | C42: Impa Stores - BA Compressor
A43: 28 | C43: Impa Stores - ACC
A44: 29 | C44: Impa Stores - Galley
A45: 30 | C45: Impa Stores - Engine
... A50: 35 | C50: Impa Stores - Instrumenation
A51: 36 | B51: GLOY-60028/26 | C51: Ultrasonic Cleaning system - 230V | D51: Stores | E51: Pending Approval | H51: To be Approved
A52: 37 | B52: GLOY-60029/26 | C52: OPA 90 KIT - 12-barrel kit | D52: Stores | E52: Pending Approval | H52: To be Approved
A53: 38 | B53: GLOY-60030/26 | C53: H.P machine - 2pcs (prefer Branded - Karcher/ KEW) | D53: Stores | E53: Pending Approval | H53: To be Approved
A54: 39 | C54: 2. LOTO Stickers
A55: 40 | B55: GLOY-60031/26 | C55: 3. Steam Splash Suit | D55: Stores | E55: Pending Approval | H55: To be Approved
A56: 41 | C56: 4. Chemical tags
A57: 42 | C57: 5. Trelleborg Safe lanes | H57: Delivered by Yard on Sws Vsl's
A58: 43 | B58: GLOY-60023/26-1 | C58: Pre Delivery - Seatab | F58: 46099
A59: 45 | C59: 8. Explosion Proof Camera
A60: 47 | C60: 10. Temperature & Pressure Calibrators
A61: 48 | C61: 11. VISWA Line Samplers
A62: 49 | C62: 12. Standard Chinese stationery
A63: 50 | C63: 13. Air driven HP Pump - For hydraulic nuts for M/E - From Dan Marine or VLINK
A64: 51 | C64: Chemical
A65: 52 | C65: Mooring Rope
A66: 53 | C66: UHF Radio
A67: 54 | C67: Soot
A68: 55 | C68: Garbage Refrigerator
A69: 56 | C69: DF Tools
A70: 57 | C70: UHF Antenna
... A77: 66 | C77: Nitrogen Generator
A78: 67
A79: 68 | C79: RSC Lube oil - qty
A80: 69 | C80: QC DC
A81: 70 | C81: Manuals for all equipment- priority for BWTS, STP, OWS, EMGCY AC, EMCY GEN
A82: 71 | C82: Domestic refrigerators 200 litres for rec rooms to be added to stores supplies
A83: 72 | C83: Breathing air compressor
A84: 73 | C84: ozone sterliser
A85: 74 | C85: suez light
A86: 75 | C86: Item no 11, loose equipment for emergency operation of roro equipment
A87: 76 | C87: Reefer cable and plugs extensions
A88: 77 | C88: Manual chain blocks
A89: 78 | C89: Glycol
A90: 79 | B90: GLOY-60035/26 | C90: Gas meters
A91: 80 | C91: Welding machine in Workshop 440 v
A92: 81 | C92: Service Car and Forlift
A93: 82 | C93: Seatrial | H93: To be Discussed
A94: 83
A95: 84
A96: 85
A97: 86
A98: 87
A99: 88
A100: 89
A101: 90
A102: 91
A103: 92
A104: 93
A105: 94
... A111: 100

Sheet tbc_project 2

Sheet Vessel 7
A1: 🚢 Vessel Purchase Order Tracker
A2: Vessel Name: | F2: ← e.g. Seaspan New York
A3: Shipyard: | F3: ← e.g. YZJ Shipyard
A4: Vessel Delivery Date: | D4: ← Enter date as: 01-Jun-2025
A6: Not Created | B6: To Be Created | C6: Pending Approval | D6: Approved & Issued | E6: Pending Delivery | F6: Delivered | G6: Total POs | H6: % Issued | I6: % Delivered
A7: =COUNTIF(E11:E110,"Not Created") -> 0 | B7: =COUNTIF(E11:E110,"To Be Created") -> 0 | C7: =COUNTIF(E11:E110,"Pending Approval") -> 0 | D7: =COUNTIF(E11:E110,"Approved & Issued") -> 0 | E7: =COUNTIF(E11:E110,"Pending Delivery") -> 0 | F7: =COUNTIF(E11:E110,"Delivered") -> 0 | G7: =COUNTA(B11:B110) -> 0 | H7: =IF(G7>0,(D7+E7)/G7,0) -> 0 | I7: =IF(G7>0,F7/G7,0) -> 0
A9: 📅 Date fields: Enter dates as DD-MMM-YYYY format (e.g. 15-Jan-2025). Columns F & G are date columns.
A10: S/N | B10: PO Number | C10: PO Name | D10: Category | E10: Status | F10: PO Issue Date | G10: Req. Delivery Date | H10: Reason / Remarks
A11: 1
A12: 2
A13: 3
A14: 4
A15: 5
A16: 6
A17: 7
A18: 8
A19: 9
A20: 10
A21: 11
A22: 12
... A110: 100

Sheet Vessel 8
A1: 🚢 Vessel Purchase Order Tracker
A2: Vessel Name: | F2: ← e.g. Seaspan New York
A3: Shipyard: | F3: ← e.g. YZJ Shipyard
A4: Vessel Delivery Date: | D4: ← Enter date as: 01-Jun-2025
A6: Not Created | B6: To Be Created | C6: Pending Approval | D6: Approved & Issued | E6: Pending Delivery | F6: Delivered | G6: Total POs | H6: % Issued | I6: % Delivered
A7: =COUNTIF(E11:E110,"Not Created") -> 0 | B7: =COUNTIF(E11:E110,"To Be Created") -> 0 | C7: =COUNTIF(E11:E110,"Pending Approval") -> 0 | D7: =COUNTIF(E11:E110,"Approved & Issued") -> 0 | E7: =COUNTIF(E11:E110,"Pending Delivery") -> 0 | F7: =COUNTIF(E11:E110,"Delivered") -> 0 | G7: =COUNTA(B11:B110) -> 0 | H7: =IF(G7>0,(D7+E7)/G7,0) -> 0 | I7: =IF(G7>0,F7/G7,0) -> 0
A9: 📅 Date fields: Enter dates as DD-MMM-YYYY format (e.g. 15-Jan-2025). Columns F & G are date columns.
A10: S/N | B10: PO Number | C10: PO Name | D10: Category | E10: Status | F10: PO Issue Date | G10: Req. Delivery Date | H10: Reason / Remarks
A11: 1
A12: 2
A13: 3
A14: 4
A15: 5
A16: 6
A17: 7
A18: 8
A19: 9
A20: 10
A21: 11
A22: 12
... A110: 100
